[
    {
        "title":"情节",
        "date":"200902",
        "content":"失魂落魄的夕阳\n仿佛沉重的叹息\n不知不觉\n步入芳草地\n\n殷勤的晚风\n传递着花香\n靓丽的花枝\n扭动着细腰\n火辣辣的目光\n直奔主题\n\n迟归的鸟\n屏住呼吸\n深陷故事的情节里"
    },
    {
        "title":"情殇",
        "date":"200804",
        "content":"一只鸟怪叫一声\n掠过头顶\n叼走我一生的幸福\n叼来了瘦瘦的冬日\n\n小丽 我把你送我的毛衣\n虔诚地套在身上\n背依冰墙 看往事\n一片片飘落\n铺成皑皑的雪原\n\n一只火狐弛过\n带给我片刻的温暖\n继而是落叶潇潇的黄昏\n以及月黑风高的暗夜\n\n小丽 你转身的一瞬\n大地就冻成了冰块\n我追赶的雪橇\n日夜兼程 一根枝桠\n在逼近夕阳的时辰\n凿穿了我那薄如蝉翼的希望\n\n风窜出了林子\n卷起石阶上的雪团\n重重地抛在崖上\n被分成无数碎块\n犹如我破碎的心\n\n小丽 那晶莹而尖锐的冰凌\n好像那无情的手指\n从那灰暗的屋檐伸来\n伸向我明亮的瞳仁\n以及温暖吐馨的昔日\n\n两杯清茶 变幻着\n克里德曼的容颜\n纯洁柔和的光芒\n象一首绝美的诗歌\n植根于我心的花园\n开出素雅的白花"
    },
    {
        "title":"秋天",
        "date":"200808",
        "content":"天高云淡\n秋水开始变蓝\n风尘仆仆的旅人\n在千里之外\n怀念一片海\n\n落叶\n卸去秋天的灿烂\n风高谈阔论\n石头沉默寡言\n鸟一只只飞离\n将大山深处的故事\n带向遥远"
    },
    {
        "title":"三闾大夫",
        "date":"200901",
        "content":"一部离骚\n砸得汩罗江\n喊疼几千年\n一部天问\n化作一柄长剑\n闪耀万世光芒\n\n三闾大夫\n你独醒的眼眸\n象一束激光\n穿越时空与阴霾\n呼啸而来"
    },
    {
        "title":"少女",
        "date":"200710",
        "content":"似乎一阵风\n匆匆来去\n仿佛一闪即逝的灵感\n留下灿烂辉煌的诗句\n\n为爱情而疼痛\n深冬之手急骤地敲门\n悬浮于龙井中的魂儿\n化一缕轻烟\n遁入季节深处\n\n雪无声地洒浇\n我以手加额\n感觉少女掩面而来\n如银白的暖风\n送我一煎梅\n玉立于月下的身影\n显得多么高贵与清冷"
    },
    {
        "title":"深刻的玫瑰",
        "date":"200710",
        "content":"恋人 走远的玫瑰\n冬天又深入了可怜的内心\n一盏灯从岁月的深处走来\n照彻我无边无际的思念\n纵然喷发一座火山\n也融化不了冰冻的情感\n一匹马固执地爬起\n从灵魂的断崖处\n踏雪而来\n\n恋人 凋零的玫瑰\n凋落我顶天立地的宣言\n曾经豪华美丽的宫殿\n变成了一片废墟\n死不瞑目的断箫\n横卧荒草丛间\n冬眠的蛐蛐\n把辉煌的歌声\n化为痛苦的呻吟\n\n恋人 刻骨铭心的玫瑰\n你在歌声中消失殆尽\n太阳椭成一把利剑\n将天空一分为二\n一半是黑暗\n一半是混沌"
    },
    {
        "title":"失血的天空",
        "date":"200808",
        "content":"一只只鸟\n抽空秋天\n失血的天空\n仿佛产妇的脸\n长满妊娠斑\n\n我张开双臂\n没有了羽毛\n细小的蚂蚁列队\n哄抬一座大山\n悠扬的号子\n在血脉里流淌\n\n我抓紧一根稻草\n又力拔一丛杂草"
    },
    {
        "title":"食物",
        "date":"200807",
        "content":"下雪天\n我搓着手取暖\n寒冷如一条狗\n蹲在暗处\n忽闪着幽光\n一块香喷喷的食物\n自助着热量\n保鲜"
    },
    {
        "title":"说出一个秘密",
        "date":"200809",
        "content":"说出一个秘密\n仿佛海底突发的火山\n试图将万吨海水烧开\n\n说出一个秘密\n一杯醇香的美酒\n挥发成水的寡淡\n\n说出一个秘密\n太阳睁大瞳仁\n似乎怀疑\n自己的判断力"
    },
    {
        "title":"碎",
        "date":"200809",
        "content":"一声脆响\n酥心的麻\n疼痛消失\n飞鸟匿迹\n甜蜜\n电流般漫过身体\n\n万道霞光\n正清理废墟"
    },
    {
        "title":"叹息",
        "date":"200901",
        "content":"沉重的叹息\n犹如一枚铁块\n掷在地上\n发出的响声\n室外能听见\n\n就象我的呐喊\n抑或清醒\n手电光一般\n射向夜空\n顶多照见\n几百米的距离"
    },
    {
        "title":"霞",
        "date":"200710",
        "content":"一片霞\n从天边飘过来\n从网叶上飘过来\n幻化为蝶\n翩跹起舞\n\n我坐在电脑前\n看翩飞的霞\n粉红的花瓣\n飘成七彩的梦\n\n一个夏天的早晨\n我目不转睛\n亲历了霞灿烂的过程\n仿佛听见嫦娥\n芬芳的呓语"
    },
    {
        "title":"献给姝丽",
        "date":"200710",
        "content":"姝丽踏雪而来\n紧握我的手\n摇了摇\n燕子就来了\n\n一只鸟栖在榆荫深处\n轻轻地唱\n当我抬起头来\n一粒清露\n正好撞上我的诗行\n袅袅的琴音\n飘向月亮的故乡\n\n羸弱的姝丽\n秋风一来就倒下了\n从此再没爬起来\n我伸出贫血的手\n被秋雨湿透极了"
    },
    {
        "title":"虚伪的碎片",
        "date":"200902",
        "content":"盛宴的狂笑\n袭击尊严\n忠诚的奴仆\n毕恭毕敬\n任刺骨的寒风\n击倒内心深处\n坚守的桅杆\n\n那些虚伪的碎片\n落红一般\n嘲弄黄昏\n疾飞的鸟\n子弹般射向辽远"
    },
    {
        "title":"雪",
        "date":"200809",
        "content":"去年的一场雪\n仍滞留心间\n今年更大的雪\n满世界狂飞\n张扬着粗野\n\n来自高空的雪\n看似多么圣洁\n以公主的姿态\n对憨厚的大地\n肆无忌惮\n\n失掉枝叶的树\n象一根巨针\n戳穿漫天的谎言"
    },
    {
        "title":"压抑",
        "date":"200812",
        "content":"夜色一样\n铺天盖野而来\n愤怒的油\n被呐喊点燃\n成燎原之势\n\n一本黄历\n密密麻麻\n写满了屈辱\n春风一吹\n蚕蚁一样爬出\n啃食尊严\n\n压抑如混凝土\n密封腐烂的植物\n躁动的沼气\n汹涌升腾着叛逆"
    },
    {
        "title":"应聘",
        "date":"200812",
        "content":"将简历递上\n渴望电光一闪\n将人生照亮\n\n更多的时候\n将网一撒\n网住的是小鱼\n无奈拾起\n填填肚子\n\n等待时机\n一旦大鱼出现\n鱼叉凌厉出击"
    },
    {
        "title":"蒸汽",
        "date":"200811",
        "content":"怨愤如蒸汽\n冲出盖\n便腾空而起\n\n在我的清醒里\n公然盗窃\n忍耐的橡皮\n越拽越长\n愈拽愈细\n\n一粒丹\n在烈焰中\n血红着眼睛"
    },
    {
        "title":"捉迷藏",
        "date":"200812",
        "content":"将眼蒙住\n凭直觉走路\n捉住的是机遇\n捉不住的是宿命\n当看透一切\n禅已深居内心\n敲响木鱼"
    },
    {
        "title":"秭归鸟",
        "date":"200901",
        "content":"抖落历史烟尘\n捎来屈子的问安\n久久盘桓\n汶川上空\n\n秭归鸟\n叫声凄厉\n仿佛尖细的银针\n深深刺进\n荒凉的废墟"
    }
]