[
    {
        "title":"白描主义：窗户",
        "date":"20160530",
        "content":"开着的时候\n怕风\n\n无风的时候\n已无法打开"
    },
    {
        "title":"白描主义：看见",
        "date":"20160530",
        "content":"白天\n看见灰尘\n\n夜晚\n看见伤痕"
    },
    {
        "title":"白描主义：苹果",
        "date":"20160530",
        "content":"好好的人生\n用刀一切\n就断了\n\n好好的苹果\n切开的时候\n里面全坏了"
    },
    {
        "title":"白描主义：破碎",
        "date":"20160530",
        "content":"左边有风\n右边也有风\n\n躲开了风\n就躲开了一场破碎"
    },
    {
        "title":"白描主义：墙",
        "date":"20160530",
        "content":"有一面墙\n怎么也过不去\n\n翻过去的时候\n墙倒了"
    },
    {
        "title":"白描主义：蔬菜",
        "date":"20160530",
        "content":"进来的时候\n它还年轻\n\n出去的时候\n它已经老去"
    },
    {
        "title":"白描主义：影子",
        "date":"20160530",
        "content":"背着光的时候\n影子在前头\n\n对着光的时候\n影子在后头\n\n走进黑夜的时候\n影子在心头"
    },
    {
        "title":"此时有风——以此诗纪念诗人张枣",
        "date":"20160530",
        "content":"我正在远离一些灰尘\n就像远离一些事非\n比如金钱，比如恐惧\n比如对面的事物\n\n一杯茶\n喝到三回\n城市的灯开始发亮\n每一扇闪光的窗户\n都是黑夜的部分\n\n此时有风\n风从窗外来\n伸出手的时候\n一不小心\n就被黑夜划破了手指\n\n我正在远离一些事非\n比如过去，比如现在\n比如未来"
    },
    {
        "title":"斗地主",
        "date":"20160530",
        "content":"一把锋利的刀\n开始卷刃\n\n过去\n它砍杀敌人\n\n现在\n也砍杀兄弟"
    },
    {
        "title":"对夏天的一次描述：八",
        "date":"20160530",
        "content":"我对这个夏天的描述\n从未开始\n我对这个夏天的描述\n也远未结束……"
    },
    {
        "title":"对夏天的一次描述：二",
        "date":"20160530",
        "content":"你看\n这个夏天的情绪正在枯萎\n路灯使这个城市的夜色\n越来越缺乏动力\n种子从树上掉下来\n庄稼失去泥土\n蚂蚁失去家园\n\n站在啤酒的一边\n看见一只蚊子在风中起飞\n我能读出他的故事\n但现在已经无法复述\n\n有人回家\n有人迷路"
    },
    {
        "title":"对夏天的一次描述：六",
        "date":"20160530",
        "content":"夏夜过去了一半\n我无法选择一个准确的词汇\n来衡量哪一半的夜\n离白天更近\n\n往后退的时候\n我看到了背影\n往前走的时候\n尚不能触摸来生\n\n此时，我很平静\n已然想不起任何往事"
    },
    {
        "title":"对夏天的一次描述：七",
        "date":"20160530",
        "content":"每个晚上\n我都用戒酒的方式检验\n哪些幸福是先天的\n哪些疼痛是后天的\n\n没有谁能够知晓\n哪一位书生\n离爱情更近\n哪一次幻想\n可以治愈影子的感伤\n\n这个夏天\n我躲在一棵树的后面\n清扫那些树叶的影子\n直到太阳落山\n\n我沿着受凉的路线\n寻找一杯夏天的热水\n有人告诉我了行驶的路径\n但目前尚没有答案"
    },
    {
        "title":"对夏天的一次描述：三",
        "date":"20160530",
        "content":"这个夏天有点儿冗长\n比一个渺茫的理想还长\n就像两条寻找河流的鱼\n在一杯啤酒的体温里游动\n始终游不到梦的家乡\n\n过去的日子都很难依靠\n就像燃尽的烟灰\n在黄昏的酒杯里\n细数着来日的银两\n\n一只猫似乎看到了苍老\n她从我身边走过去\n没留下任何声响"
    },
    {
        "title":"对夏天的一次描述：四",
        "date":"20160530",
        "content":"此时，你如果不了解\n一杯啤酒的伤感\n你就无法知道\n我离这个夏天该有多远\n\n我想用一棵芹菜的高度告诉你\n在大米不能到达的世界里\n距离会变得寒冷\n厨房也会变得头痛\n\n没有谁能使怀旧\n变得像馒头一样饱满\n当你不能安抚这夏夜的虫鸣\n请学会用盐开路\n用酱油和醋\n料理这一年一度的人生"
    },
    {
        "title":"对夏天的一次描述：五",
        "date":"20160530",
        "content":"没有风\n时间把日子铺上了一层\n厚厚的灰\n\n再往前走两步\n就听到了风声\n就触摸到了容器中的水\n并看到了一棵草的生长\n\n这个夏天\n我以每天一瓶啤酒的速度\n无限接近真理\n然后\n我在房前种下白天\n在屋后种下黑夜\n\n我躺在房屋的深处\n等待着一场\n从白天刮往黑夜的风\n\n那个从风中走过的人\n既不是我的家人\n也不是一位故人"
    },
    {
        "title":"对夏天的一次描述：一",
        "date":"20160530",
        "content":"我想把夏天关进瓶子里\n隔着玻璃让日期失效\n日子是一块遗弃的瓜皮\n上面爬着黑色的蚂蚁\n\n水不按常理流动\n没有谁看到它的去向\n在夏天，我不想想起谁\n也没有谁会想起我\n\n这个时节有风\n风吹动了窗户"
    },
    {
        "title":"感冒十章：吃馒头",
        "date":"20160530",
        "content":"吃了多年的米\n突然吃了个馒头\n觉得很好吃\n\n我一连吃了五个\n一下子就撑醒了"
    },
    {
        "title":"感冒十章：抽烟",
        "date":"20160530",
        "content":"天黑下来的时候\n没烟了\n\n我把黑夜卷起来\n当烟抽\n\n燃起的烟雾\n飘到了白天\n\n其实我不是一个\n在白天抽烟的人"
    },
    {
        "title":"感冒十章：感冒",
        "date":"20160530",
        "content":"感了一次冒\n把日子丢了\n\n看了一眼电视\n把自己丢了\n\n睡了一觉\n被疼醒了\n\n现在\n我在等一个电话"
    }
]