[
    {
        "title":"你无法模仿我的生活：得知安马或马安对话皆成文本，马氏即兴打油一首，诗曰——",
        "date":"2009",
        "content":"马上相逢无纸笔，凭君传语打油归。马鞍不卸劳鞍马，古来斗嘴几男回？"
    },
    {
        "title":"你无法模仿我的生活：得知马氏即兴打油一首，安氏也不甘示弱，即兴回击，诗曰——",
        "date":"2009",
        "content":"脑子一紧张，灵感跑光光；好马要好鞍，坏马也得装。"
    },
    {
        "title":"你无法模仿我的生活：对话跟丢了的你",
        "date":"2009",
        "content":"——真想技术革新，我觉得用不了一个五年计划。\n——你这样跟着很快就会顿悟了。\n——我不是在课堂坐得住的人，跟在人后肯定会跟丢。\n——那就叫丢人。"
    },
    {
        "title":"你无法模仿我的生活：对话旷日持久的你",
        "date":"2009",
        "content":"——我本就只有三板斧，又好些年头不耍了，果然就过时了。但我想，接近那些现\n代派也用不着云梯，也用不着旷日持久吧？\n——中国诗歌讲究顿悟，或者说中国智慧讲究顿悟。所谓一念之间，心想事成。"
    },
    {
        "title":"你无法模仿我的生活：对话无从授法的你",
        "date":"2009",
        "content":"——你无法模仿我的生活。\n——无法之法，无从授法。当然就无法模仿了。"
    },
    {
        "title":"你无法模仿我的生活：对话修辞中的你",
        "date":"2009",
        "content":"——近日正研读老子、孙中山，顺便也研读你。\n——修辞学里有一种叫“不伦之比”的手法。你把我跟他们放在一起，就有这样的\n修辞效果。\n——生命轮回，很难说你跟他们就没有关系。"
    },
    {
        "title":"你无法模仿我的生活：飞机，再见",
        "date":"2009",
        "content":"弃我去者，昨日之日不可留\n乱我心者，今日之日在天上\n飞机，再见！祝他在家乡牛羊不归\n妻妾成群。我只愿\n故园三千里\n深宫二十年。"
    },
    {
        "title":"你无法模仿我的生活：风动了又动",
        "date":"2009",
        "content":"他一如既往，他嬉皮笑脸，他孩子气地向你告别\n他让你顿时发窘，暗叫惭愧。你曾用诅咒爱他\n用恨爱他，用自虐爱他，用涂抹黑色爱他\n用一团糟的心绪爱他。用不爱\n爱他。"
    },
    {
        "title":"你无法模仿我的生活：孤独颂",
        "date":"2009",
        "content":"白日可以放歌，\n夜晚无处欢爱。\n流年尽管似水，\n此生原本遗憾。"
    },
    {
        "title":"你无法模仿我的生活：关于“识荆”的错乱轮回",
        "date":"2009",
        "content":"——我深知先锋对人本性的破坏会大于它对人的塑造，它让你在看到更为纷繁破碎\n、瞬息万变、玄秘凌乱的世界的同时也将剥夺你原始的本真的哪怕是无知也好的安\n宁。这也是我想对你说的。\n——是警告，还是……？\n——是可能的事实。先锋很破坏人，中国古典安慰人。\n——我对先锋充满敬意，但也许我不会被挑选到前排。\n——也许会“身不由己地去了”。\n——那就揪出那看不见的第三只手看看，当做“识荆”或“塞壬”。\n——惭愧，只知“负荆”不知“识荆”，正在百度。原来是李白的“生不用封万户\n侯，但愿一识韩荆州”啊，居然是我前前前夫说的。\n——前前前夫？你也作古了吗？\n——难道你不记得春秋时期某个雨夜路过你驿站的那个女扮男装的男子，那就是我\n。\n——那可能是你记错了，我只记得曾经为一位女士大老远地送荔枝。\n——真狠心啊，累坏了老马家好几匹马啊。\n——你吃过那荔枝吗？\n——我们家单于不让吃。\n——那就真不知道“昭君姑娘”是怎么养颜的了。\n——以泪洗面嘛。\n——那也是“此泪只应天上有，人间胜似洗面奶。”"
    },
    {
        "title":"你无法模仿我的生活：黑暗或者你",
        "date":"2009",
        "content":"脑子已锈恰如心已木，全身无感恰如\n黑在暗中黑，我中有你时。"
    },
    {
        "title":"你无法模仿我的生活：嘿，驿站长",
        "date":"2009",
        "content":"嘿，驿站长，你可曾看见我的马，它驶过长亭又驶过\n短亭。红色的棕毛在风中绝尘马蹄声声踩踏我的意志\n我的左心房，它席卷而去我的魂魄我的失魂落魄\n我的驿站长！"
    },
    {
        "title":"你无法模仿我的生活：后人挖你之后——",
        "date":"2009",
        "content":"挖吧，白骨一堆而已，没有殉葬的金银。"
    },
    {
        "title":"你无法模仿我的生活：忽然还是突然？",
        "date":"2009",
        "content":"——想到你说“明天将出现什么样的词”，我就忽然也想到一些词。\n——你喜欢用“忽然”，很优美，我一般用“突然”，很杀人。"
    },
    {
        "title":"你无法模仿我的生活：极限体验：再任性下去",
        "date":"2009",
        "content":"人们都不爱看见黑暗：或者看不见，或者视而不见。\n就像人们都认为，应该表达爱，美好，温暖而不是，它们的反面。\n我恰好是既看得见又喜欢把看见的表达出来的人。无论爱还是不爱，无论黑暗还是\n光明。\n我所有的诗歌基本都是生活真实而非寓言，我的生活本身就很寓言了。\n我唯一的幸福和幸运就是：我能表述。"
    },
    {
        "title":"你无法模仿我的生活：记得多年前舒婷说过，有家底的表现之一是：有十几年的老友。",
        "date":"2009",
        "content":"许久未让伟雄来电解忧，今日在华灯初上的街头故伎重演，听他一以惯之的劝慰夹\n杂时常伴随的雄浑呵呵声不禁感叹，毕竟15年老友，知我强悍，也知我脆弱，知我\n良善，也知我任性。我庆幸在写作《永远未完成》时凭着本心的驱使恢复了和伟雄\n、宜兴的感情。此前我和他们怄气已近一年（伟雄说，是我跟他们怄气，他们可从\n来没跟我怄，想想也是，一年来问候、寄茶叶他们都一如往昔）。无论如何，他们\n是最纵容我的兄长，我希望今后他们对我提醒再多些，严厉再多些，不要让我太走\n极端。"
    },
    {
        "title":"你无法模仿我的生活：借用你，一点灵感",
        "date":"2009",
        "content":"那些未曾谋面的灵感深藏在\n未曾谋面的某人身上\n未曾到来的曲线、直线，抛物线\n未曾到来的菱形、圆形，正方形\n未曾被爱的你，已经在爱。"
    },
    {
        "title":"你无法模仿我的生活：今日无事",
        "date":"2009",
        "content":"你在场我当你不在场，前日无事\n昨日无事今日——\n必也无事。"
    },
    {
        "title":"你无法模仿我的生活：惊飙从天降，好马知时节",
        "date":"2009",
        "content":"正当天空艳阳绽放，北方一日三晴，春天到了\n你拍着胸脯，呼出郁闷之气你说\n春天到了，好马知时节\n惊飙从天降。"
    },
    {
        "title":"你无法模仿我的生活：决不让崩溃胜利！",
        "date":"20090416",
        "content":"正如我对你说的，我不知为何这般分裂，总是控制不住地人前激情而其实内心几近\n崩溃。"
    }
]