[
    {
        "title":"有多少爱",
        "date":"20021018",
        "content":"耳朵是多余的\n请割掉\n心脏是肮脏的\n请挖掉\n\n这是我给你们的尖刀\n把自己修理一下\n请听我唱\n“有多少爱。”"
    },
    {
        "title":"有两个人接吻",
        "date":"20021018",
        "content":"那是在华飞路\n我刚刚从另一条路拐过来\n要去邮局\n劈面看见两个人抱在一起\n年纪很小的样子\n抱得那么紧\n看来十分悲伤\n我这样想是因为\n在十年前\n在一个小镇的火车站\n我也和一个人这样抱过\n只有悲伤才能这样\n抱着\n唯一的区别是\n有一辆自行车\n摔到在脚下"
    },
    {
        "title":"有什么意思呢",
        "date":"20020930",
        "content":"外面的雨很大\n外面的雨\n是什么意思呢\n是不是\n有里面的雨？\n如果有的话\n有什么意思呢"
    },
    {
        "title":"有时候，我会一个人在房间里赤身裸体走来走去",
        "date":"20040719",
        "content":"不看镜子\n感觉着空气在身上游走\n阴茎会适时涨大\n在两腿间晃来晃去\n有时候\n我会用手摸一摸\n加上一些遐想\n当它软下来\n觉得已经成为一个女人\n而心疼"
    },
    {
        "title":"有朝一日，我将随风而去",
        "date":"20041118",
        "content":"风在空中\n你看不到它\n只是吹着\n\n风在推着你\n在左边\n或者右边\n\n有时在前面\n在后边\n在头顶的时候\n不如在脚下\n\n让你感到冷\n让你不停地打寒战\n站不稳"
    },
    {
        "title":"雨山湖的雨",
        "date":"20021024",
        "content":"我们在拍照的时候\n身后的桂花树\n沙沙地响了起来\n小兰说雨来了\n我们就看见\n雨丝从小桥那边\n斜斜地跑过来\n落在水面上\n渐渐地跑到湖中央\n然后\n整个雨山湖就都挂满了\n雨丝"
    },
    {
        "title":"雨山路上",
        "date":"20030619",
        "content":"雨山上的鸟 已经\n飞起来\n扑喇喇的声音\n正传过来\n\n雨山湖的鸬鹚 还静静地\n蹲在枝桠上\n盯着水面\n还没有飞起来的意思"
    },
    {
        "title":"雨天",
        "date":"20040909",
        "content":"雨很大的时候\n我喜欢离开\n到处走走\n这个城市变化很大\n让我有些陌生\n偶尔接到一个电话\n说是要聚聚\n我能说什么呢\n有些事情可以放开\n在下个月\n或许可以抽出点时间\n在一起\n抽烟喝酒\n然而这两样都不是我\n擅长的"
    },
    {
        "title":"预感",
        "date":"20031003",
        "content":"我有种预感\n我会死\n但不是很普通的死\n也不是在今年死\n可能是明年\n也可能是后年\n不是病死\n也不是被汽车撞死\n而是自己找死\n一个人死\n一个人\n静静地\n看着\n自己慢慢死\n但可能\n看不到自己最后的\n一口气\n是进还是\n出"
    },
    {
        "title":"浴缸坏了",
        "date":"20030901",
        "content":"狗子家的浴缸\n裂了一条缝\n这是洗完澡后看到的\n是以前坏了还是\n刚刚坏的\n我没问\n我跟狗子说\n你家的浴池太小而且\n很滑\n差点摔了我一跤"
    },
    {
        "title":"月亮",
        "date":"20020930",
        "content":"象一张脸庞\n微微的\n有点红\n但是慢慢地\n就变白了\n因此她也是\n平静的\n还不是很圆\n但是再过两天\n就会圆了\n那时会看到地下\n有一条巷子\n有一棵松柏\n一群人向上面看它\n中间还有一头\n走来走去的\n驴子"
    },
    {
        "title":"在暗夜里漫游",
        "date":"20170308",
        "content":"世人都沉入\n梦境\n偶尔有翻身 咳嗽\n也有梦游\n在睡眠之下\n一切痛苦 幸福\n随风而逝\n一个在深夜行走的人\n他能听到\n自己的心跳\n也能看见黑暗的帷幕\n包裹着他\n如同包裹着一个\n婴儿"
    },
    {
        "title":"在车站广场",
        "date":"20021018",
        "content":"如果我死了\n（这想法很棒，很吸引人）\n象条死狗一样\n趴在地上\n广场上的人都颠颠地跑过来\n有人穿过尖利的汽车喇叭声跑过来\n甚至 几条街道之外的人\n也会相互吆喝着结伴而来\n里三层外三层\n他们肯定议论纷纷\n（你要不要哭泣，看着办吧）\n直到警察用粉笔画好我的姿势\n把我拎走\n\n想着想着我就\n软了\n但没有趴下来\n只是蹲下来"
    },
    {
        "title":"在城郊，看到久违的蝴蝶",
        "date":"20021018",
        "content":"我看到了蝴蝶\n三只 白色的\n它们把翅膀煽得很夸张\n也是白色的\n\n田野里有些蔬菜\n不象以前那么绿了\n不知道\n飞来飞去忙些什么\n\n远处肯定也有\n肯定也在忙着什么\n没准\n也是白色的"
    },
    {
        "title":"再见，姐姐",
        "date":"20030901",
        "content":"当时天阴，风很大\n我说\n毛主席死了怎么办\n你说不知道\n然后我们站在船头\n看辽阔的北塘\n象看着整个国家\n这都是真的\n1976年 我们都还小\n但懂得悲伤"
    },
    {
        "title":"再见，妈妈",
        "date":"20031003",
        "content":"下楼梯\n右转\n我看见你靠在墙上\n一动不动\n这很好\n多晒太阳好\n我这就走了\n下次回来\n如果太阳还晒着你\n我会很开心"
    },
    {
        "title":"再见，马鞍山",
        "date":"20021018",
        "content":"骑一匹马\n翻过一座山\n（而不是仅仅骑马\n或翻一座山）\n山坡上绿草如茵\n山顶上白雪皑皑\n我会在山顶上停下来\n四下看一看\n也许什么也看不到\n然后 轻抖缰绳\n让马从另一个山坡\n啼嗒而下"
    },
    {
        "title":"在九楼",
        "date":"20150705",
        "content":"每次站在阳台上 我都喜欢\n探身栏杆之外\n俯瞰着地面 俯瞰着\n移动的小人\n滑行的黑色车辆\n还有那些拼命生长的树\n每次站在阳台上 总希望\n有一群鸟儿飞掠而过\n叽叽喳喳 好像在交谈什么\n好像这世界依旧美好\n哪怕孤单单的一只 也是好的\n我喜欢站在阳台上 想一些\n不相干的事情\n风来的时候 使劲扯着我的头发和衣服\n像是命令 更像是邀请\n去到另一个世界"
    },
    {
        "title":"在宿州",
        "date":"20050417",
        "content":"宿州的街道\n灰尘比南方要多\n树也稀罕\n宿州的人民说着\n我不太明白的话\n管 或者不管\n其实在多年前\n已经听过\n但是不习惯\n我开始咳嗽\n也认不清方向\n我准备\n明早好好看看太阳\n它到底在哪里\n升起"
    },
    {
        "title":"在希尔顿酒店",
        "date":"",
        "content":"长江一定是凉爽的\n泊在长江上的轮船肯定也是\n凉爽的\n它们动都不动\n安逸极了\n酒店外的树\n也是凉爽的\n看看那些晃动的树叶\n就知道了\n\n外面的情景\n让里面的人越发闷热\n都在喊热\n这是三十年同学会\n我写下这首诗\n还能想象当时的情景\n体会到那种热\n从里到外的不安"
    }
]