[
    {
        "title":"安娜",
        "date":"",
        "content":"——与忧郁的对话\n\n「这种东西就像是下午一样\n你不去管它，它一下就变暗了。」\n\n安娜这么说着的时候\n我看见她眼中空白的情绪\n和我自己褐色的倒影\n漂浮聚集在她失焦的眼珠上\n几乎就将化做被遗弃在大海中央的一滴泪\n那是难以辨识的存在与疑惑\n我无法揣度安娜正在想着些什么？\n\n而安娜或许什么也不想\n譬如每天午餐过后\n我总是陪着她看着空无一物的餐桌\n像是看着一幅素描的静物划\n渐渐地才感到饱足\n安娜什么都不说\n好像沉默也把我们一起吃了下去\n\n而安娜或许什么都想\n坐在窗边若有所思的时候仿佛也若有所失\n好像所有的事物都背对着她藏匿一个秘密的远行\n有时她会意味深长地对着我微笑\n似乎在我身上找到了像钥匙一般的东西\n这让我感觉我更像是一个门\n而我不知道门的另一边是什么样的风景\n安娜开启了我去到了哪里\n\n而安娜或许哪里也不去\n她背对着我们构思不存在的旅行\n所以没有去或不去的难题\n没有快乐或不快乐的困境\n安娜只是用她生命里全部的倾斜将世界举重若轻\n像是另一个偏着头自转的行星\n慢慢地旋离整个太阳系\n\n那一天安娜的眼轻轻合上的时候\n我把她的声音拖曳进这首诗里\n她说：「这种东西就像是下午一样\n你不去管它，它一下就变暗了。」\n（请念出声音，这是最初的话语。）\n\n现在我反覆思忖着安娜说着这句话时的模样\n渐渐了解那是什么样空白的情绪……\n也许当天色已经暗得不能再暗的时候\n当月光倾斜到不能再倾斜的时候\n总有些什么即将醒来\n总有些什么会被记起\n\n安娜仿佛钥匙一样插入我的生命\n打开一扇通往□□的门\n（请填上它，这是最终的困境。）\n\n最初的话语就是最终的困境\n日子顺序前进如杂草伏地蔓生的图形\n而安娜停在这里\n像一只忧郁的蜻蜓"
    },
    {
        "title":"归线往南的忧郁",
        "date":"",
        "content":"如果你前来\n像一座寂寞的冰山私自漂离极地\n勇敢是涛，梦想是浪\n沿着虚拟的航线，向南。崩解，渐次沉没。\n如果你离去\n躺下一张线条简单的床\n在入梦前抛弃自己的轮廓\n幻觉与美好，都已备妥\n遥远的乡愁，向南。噤声，顺势沉默。\n或许仅仅是南方的港口把我丢掷在港口的南方\n某种缺席的邀请述说着\n有些人前来，有些人离去\n这样的事件仿佛风暴过后的西南气流\n我无法指认每一次它带着庞沛水气的回归\n是否如同往年一般漫漶着难以理解潮湿的记忆\n于是我想象一种空白的时刻\n风听见风，落下。高温的呓语，等待\n在失序的城市座标中\n充满方向感的免疫力\n像是路过时彼此约略点头交换气味的蚁群，无言\n但是了解\n了解那样一种归线往南的忧郁\n南方的想象是一张航向温暖乐音的琴\n勇敢是弦，梦想是弓\n音符与和声都已备妥\n而我把自己像沙漏一样倒过来\n等待生命某种从无到有或说是从有到无的过程\n并在细微的声响里分辨哪些是爱过的\n哪些是还未曾爱的\n想到这里的时候，我仿佛\n不再孩童般地否认一个令人难堪的胎记\n也不再成人般地强调一种装饰过后的口音\n南方的港口把我丢掷在港口的南方\n无论前来离去，记忆\n像是浪潮雕塑着不安的海岸线\n被遗忘而界定\n于是我想象我的双手圈起一个海域\n豢养着一座无人探访的孤岛\n而你是被我剪掉的指甲\n再过一星期就长回来了。"
    }
]