[
    {
        "title":"口语诗",
        "date":"20201020",
        "content":"公众号选稿\n发了一组过去\n今日看到这期\n没我的诗作\n心里挺纳闷儿\n这组质量还不错啊\n咋会没有入选呢\n回看邮箱\n我操\n投给2019年度"
    },
    {
        "title":"口语诗年鉴",
        "date":"20201011",
        "content":"收稿邮箱了\n须知\n那地方早已\n人去楼空\n达一年之久"
    },
    {
        "title":"口语诗人",
        "date":"20191017",
        "content":"妻子帮我\n买了件羊毛衫\n一听说打折后\n820块钱\n赶紧警告她\n“太贵了\n以后再帮我买的话\n每件不能突破500”\n“为啥\n难道穿好了\n还丢你人吗”\n“对！\n穿好了\n会让我觉得\n自个儿不是\n口语诗人”"
    },
    {
        "title":"口语诗人不仅会写诗还得会生存",
        "date":"20200223",
        "content":"在防控卡口\n值大夜班\n晚上12点过后\n再没人走动\n决定睡会儿\n自带的被子太小\n帐篷里没法儿睡\n（一张行军床\n被人占据\n得打地铺）\n摸到30米开外的\n社区办公楼里\n在值班室的\n木质沙发上\n铺开被子\n躺下试了试\n硌背\n巡视一圈\n发现墙脚一个纸箱里\n有几套没开封的\n保安制服\n一袋袋排开\n再睡\n果然\n舒服些了"
    },
    {
        "title":"口语诗选",
        "date":"20201011",
        "content":"在一组口语诗选中\n突然读到几首\n貌似口语诗的\n非口语诗\n仿佛\n吃饭吃到\n几颗白色石头子儿\n让人不得不啐出\n满口的饭不说\n关键还把我牙\n给硌疼了\n以后\n这牌子的大米\n咱再也不买它"
    },
    {
        "title":"口罩",
        "date":"20210703",
        "content":"路边停着的\n几辆货运\n机动三轮车的\n挡风玻璃后面\n都挂着一只\n一次性口罩\n搬运工们\n坐在旁边\n玩着扑克"
    },
    {
        "title":"口罩价格",
        "date":"20210129",
        "content":"单位给每个人\n发了100个口罩\n有同事\n随口问了声\n“多少钱一个”\n后勤科长说\n“这是好口罩\n可不比外面街上\n那些推着叫卖的\n15块钱\n就能买两包”"
    },
    {
        "title":"口罩与酒",
        "date":"1000",
        "content":"下午上班\n在十字路口\n又遇到那几个志愿者\n其中一个在发牢骚\n“妈的\n我本来好心\n想促进下宣传效果\n跟分管财务领导说\n买几包口罩\n分发给那些\n没戴口罩的路人\n你猜他怎么说\n‘只准买几个\n你们自己用\n路人不要管\n不许乱花钱’\n说得比唱得\n还好听\n上次\n他招待客人\n人家已经喝好了\n他又去拿了一瓶\n20年白云边\n都够买"
    },
    {
        "title":"口罩，口罩",
        "date":"20200609",
        "content":"既然周围\n没有新增病例\n且无症状感染者\n又不传染人\n我想\n在不让摘下口罩的情况下\n那我个人是不是\n可以选择\n一个口罩\n戴它个十天半月\n何必浪费资源呢\n事实上\n我戴的这个口罩\n已经是第5天了"
    },
    {
        "title":"哭丧",
        "date":"20200521",
        "content":"舅舅去世\n堂舅妈前来吊唁\n离冰棺还有几米\n就踉跄起来\n并嚎啕大哭\n“我可怜的哥啊……”\n早些年\n堂舅在世时\n他们几乎无时不刻\n都想着\n怎么占舅舅家便宜\n两家人吵架\n成为家常便饭\n他们甚至动过\n杀死舅舅的心思"
    },
    {
        "title":"哭声",
        "date":"20201204",
        "content":"外孙出生\n半月来\n饿了哭\n渴了哭\n拉了哭\n尿了哭\n哭声\n听多了\n以致于\n临晨5点多\n楼下小车\n打火启动\n都被我当成\n外孙在抽泣"
    },
    {
        "title":"枯心",
        "date":"20201016",
        "content":"老家有个村民\n外号枯心\n其意思是\n凡事做得绝\n昨儿小妹告诉我\n他家那栋3层小楼\n顶层卖给了\n他女婿大哥\n这人46了\n至今还是单身\n也不知道啥原因\n搬过来后\n交往过几个女人\n竟然都没处上\n再这么下去\n很可能单身\n一辈子了\n枯心独一个女儿\n女婿早些年入赘过来了\n女婿大哥如果无后\n这份房产\n其他兄弟姐妹\n肯定抢不走了"
    },
    {
        "title":"苦",
        "date":"20190317",
        "content":"妻子买回\n一把野菜\n焯水过后\n入锅炒好\n端上饭桌\n跟她两人\n一人一筷\n我说\n“太苦了”\n妻子说\n“是呀\n太苦了\n苦得吃不下去”\n边说边起身\n拿去倒掉了\n我心说\n如果回走40年\n比这更大的苦\n也能吃下去"
    },
    {
        "title":"苦孩子",
        "date":"20200421",
        "content":"女儿怀孕后\n身体出现不适\n跟单位申请网上办公\n便于呆在家里养胎\n获批之后\n从长沙回来\n跟我们生活\n不禁想起\n小时候\n生产队里那些\n怀孕的女社员\n即便临盆\n仍旧要在田间劳作\n曾经不止一次出现\n在田间地头\n生孩子的情景\n唉\n那时出生的孩子\n（包括我在内）\n打胎儿起\n过的就是\n苦日子"
    },
    {
        "title":"苦黄瓜",
        "date":"20190630",
        "content":"一盘黄瓜片\n有点儿苦\n我说倒掉算啦\n母亲坚持要吃\n我说\n“您老胃不好\n要吃就给我吃吧”\n母亲端起盘子\n一股脑儿\n全都倒进\n父亲碗里\n“你也别吃\n都给你爸”"
    },
    {
        "title":"苦命人",
        "date":"20210414",
        "content":"一辆走街串巷\n卖洛川苹果的\n小货车\n转到门前\n25块钱\n买了一袋\n微信支付\n看货主昵称\n叫“干就完了”\n我说这个名儿\n挺有意思\n他说没办法\n咱是苦命人\n不干就没饭吃\n猛然想起外孙\n女儿女婿当初\n给他起名“直就”\n意思是\n想好了直接就做\n不要等待和犹豫\n妻子也曾说\n这名字不好\n预示命苦"
    },
    {
        "title":"苦笑",
        "date":"20201224",
        "content":"办公室工作人员\n拿着份文件进来\n问我知不知道\n上面布置的工作\n接过匆匆看了几眼\n告诉她\n“这不是我分管的”\n“那是谁分管呢\n给几个领导看时\n他们都让我\n拿给您看看”\n正要给她支招儿\n忽然想起\n早上妻子叮嘱过我\n“刚看了星座运势\n你今天运气很背\n千万别去掺和\n别人的事情\n否则\n只会给自己\n带来麻烦”\n于是我摇摇头\n给了她个苦笑"
    },
    {
        "title":"酷",
        "date":"20200505",
        "content":"下班回家\n在家属院\n看到两个\n五六岁的\n一男一女\n两个小孩儿\n在健身器材上玩耍\n其中的小男孩儿\n把口罩拉下\n将下巴\n兜着\n猛看过去\n挺酷的\n想笑\n没笑出来\n记得几天前\n见到他父亲\n也这个样子"
    },
    {
        "title":"夸奖",
        "date":"20210625",
        "content":"轮椅推着父亲\n在小区内转悠\n遇到个大姐\n问了问父亲情况后说\n“你爸还是有福气\n你们姊妹几个\n都很讲孝道\n把他照顾得很好\n他要是生在别的家庭\n我看至少死了三回”"
    },
    {
        "title":"夸瓢",
        "date":"20200816",
        "content":"二叔孙女\n考上大学\n一大早\n他来家里\n邀请我参加\n下个星期天\n举办的贺宴\n一开口就说\n“不需要你\n花一分钱\n你送礼钱\n我也不要\n就希望你\n到时候\n去宴席上\n露个面儿”\n不禁想起\n在我小时候\n生产队社员\n因为二叔\n嘴巴子太能说\n给他起了个诨名\n“夸瓢”"
    }
]