[
    {
        "title":"收废品的",
        "date":"20210714",
        "content":"小妹夫下工回来\n正要进门\n手机响了\n一个女人声音\n“你是不是收废品的”\n“我收团鱼”\n小妹夫\n没好气回了句\n把电话挂掉了\n然后冲我说\n“抹了一天灰\n人都快累死了\n她倒好\n说我是收废品的\n真要做那么赚钱的生意\n那就好咯”"
    },
    {
        "title":"收割机",
        "date":"20200818",
        "content":"又到收割季节\n绕城公路上\n收割机\n一辆接一辆开过\n每一辆收割机上\n在男驾驶员身边\n坐着一个\n捧着手机\n追剧的女人"
    },
    {
        "title":"收工",
        "date":"20210525",
        "content":"傍晚\n在家属院施工的\n几个工人\n开始收工\n临走之前\n把他们的工具\n全都塞进了花坛里\n邻居跟他们开玩笑说\n“你们搁这儿\n万一被人拿走呢”\n“不可能\n知道我们藏这儿的人\n谁也不会要它们\n想要它们的人\n又不知道藏这儿”"
    },
    {
        "title":"收货",
        "date":"20210802",
        "content":"妻子给我网购的\n一箱24罐黑啤\n快递送到家\n外包装纸箱\n已不成样儿\n快递员\n帮忙划开\n发现少1罐\n破了7罐\n另外没破的16罐\n有5罐已经严重变形\n剩下11罐也有磨损\n如果选择退货\n估计店家到时\n一罐也落不着\n快递员建议退货\n我说\n“算了\n店家已冲我老婆\n说了一大堆好话\n做生意也不容易\n我将就着收下吧”"
    },
    {
        "title":"收旧货",
        "date":"20200322",
        "content":"下午3点多\n窗外突然飘进\n回收旧电器的叫买声\n“这人真的赚钱不要命啊\n疫情还没完全消散\n就敢出门收旧货\n你想想看\n前段时间\n得了新冠肺炎的人家\n肯定少不了趁机\n淘汰旧电器”\n妻子的话\n让我\n不寒而栗"
    },
    {
        "title":"收看警示片",
        "date":"20210705",
        "content":"早上一到单位\n党办主任就通知我\n“10点钟收看警示片”\n“我已经不是领导了”\n“不还有职务犯罪吗”\n“问题是\n我现在啥也不管啊”\n“你不还是党员吗\n给思想上敲敲警钟\n也是好的”"
    },
    {
        "title":"收视费",
        "date":"20191125",
        "content":"有线电视台\n电话通知我\n父母的收视费到期了\n回家拿上上次缴费发票\n去到缴费大厅\n询问工作人员\n“我3月份缴的\n才8个月\n咋说到期了”\n她问了我电话\n调出电脑里的数据\n“没错\n你是3月16日缴的\n但你初次缴费时间\n是2006年11月23日”\n“问题是去年11月\n到今年3月这段时间\n我没续费\n你们也没送信号呀”\n“那没办法\n系统默认的\n是以前的日期\n我们也改不了”"
    },
    {
        "title":"收头发",
        "date":"20201219",
        "content":"收头发的男人\n在家属院里\n兜了一圈儿\n一无所获\n又出去了\n忽然想起\n母亲屋后\n小菜园里\n那块韭菜\n整个冬天\n基本上\n停止生长"
    },
    {
        "title":"收衣服",
        "date":"20191221",
        "content":"下午帮父亲洗完澡\n顺便把他衣服也洗了\n晾在门前衣架上\n晚上没干\n母亲要收进屋\n挂在阳台上\n小妹说\n“都是些旧衣服\n搁在外面没人要的\n免得收进拿出的”\n“那是呢\n现在再好的衣服\n放在外面也没人要”\n母亲边说边不停地\n把衣服从衣架上\n一件件取下来"
    },
    {
        "title":"收租婆",
        "date":"20210101",
        "content":"大妹给侄女\n介绍了一个男生\n两人处了几个月后\n侄女说那男生\n没有上进心\n大妹说\n没上进心怕啥\n他家有两处门面房\n还怕以后嫁过去\n把你饿着了吗\n你只要当收租婆\n就行了\n侄女犹豫了\n整整一个星期\n最终还是放弃了\n当收租婆的机会"
    },
    {
        "title":"手感",
        "date":"20200413",
        "content":"路边摊上买苹果\n女摊主称重后\n跟我打商量道\n“给你加两个\n小个儿的\n凑30块钱吧”\n掏钱的工夫\n瞥了眼电子秤\n上面显示\n31.24元\n给她30块钱后\n又拿出一块钱零钱\n递过去\n女摊主连连摆手\n“不收了！不收了！\n说好30就只收你30\n多出的那一块钱苹果\n算我送你的\n要怪\n也是怪我自个儿\n手感不准”"
    },
    {
        "title":"手工",
        "date":"20200827",
        "content":"女儿午休还没起来\n妻子拿起她搁在沙发上的\n一个快要编织完的小手工\n看了看说\n“我猜啊\n咱们女儿怀的\n一准儿是个女孩儿”"
    },
    {
        "title":"手环",
        "date":"20210713",
        "content":"妻子去协和医院\n探望二姨子\n被保安拦住\n要求出示近期\n核酸检测证明\n这么一来\n肯定进不去了\n旁边一个好心大姐\n悄悄给妻子支着儿\n“你想办法\n把病人的手环\n让人给带出来\n你带着它进出\n就没人拦你了”"
    },
    {
        "title":"手机",
        "date":"20210110",
        "content":"吃完早餐\n妻子发现\n她手机没看见\n拿起我的手机\n一遍遍拨打\n一点儿声音\n都没有\n忽然想起\n有次\n我俩吵嘴后\n好几天没讲话\n她一遍遍戳我\n都没理她"
    },
    {
        "title":"手机定位",
        "date":"20210314",
        "content":"陪父母\n坐在门口聊天\n一个快递小哥\n突然停下来\n心里不免纳闷儿\n父母又不会网购\n忍不住问他\n“谁的快递”\n“58号的”\n“58号在前排”\n“我手机定位\n是在这儿”\n他起抬头\n看了眼门牌号\n把车开走了"
    },
    {
        "title":"手机收到消防大队编发的短信",
        "date":"20210304",
        "content":"“关注俩会\n关注消防\n俩会期间\n请各单位\n严格落实\n消防安全责任\n及时维护保养\n消防设施\n确保完好有效\n同时加强值班巡查\n保证安全出口畅通\n及时消除\n火灾隐患”\n是啊\n消防责任重大\n那俩会过后呢"
    },
    {
        "title":"手机天气预报",
        "date":"20210331",
        "content":"午夜醒来\n记录梦景\n屋外\n狂风怒吼\n暴雨如注\n写完之后\n顺便看了一眼\n手机天气预报\n我操\n上面显示的\n竟然是阴天\n还有一团白云\n从屏幕上飘过\n不禁心生疑窦\n难道手机报的\n是室内天气吗"
    },
    {
        "title":"手帕",
        "date":"20210117",
        "content":"父亲痴呆\n一年多\n因为吃药\n时常流口水\n母亲给他做了围兜\n想着母亲年纪大了\n洗围兜也不轻松\n建议母亲\n跟我们小时候样\n在父亲肩部头\n用别针\n别上个手帕\n方便擦口水\n母亲说\n哪儿用得着手帕呀\n给他围兜里面\n塞几片纸巾备着\n就行了"
    },
    {
        "title":"守山",
        "date":"20210404",
        "content":"母亲姨表哥\n大街上\n碰见舅表弟\n跟他打听\n舅舅情况\n舅表弟说\n“他登山去”\n“哪还不错哦\n80好几的人\n还能登山”\n“是不错呢\n已经在山里\n呆了快一年”\n表伯还没意会\n接着问舅表弟\n“在哪座山呀\n他去哪儿干什么”\n“您说他能干什么\n守山呀\n正月里面\n把我妈也\n接过去了”"
    },
    {
        "title":"手无缚鸡之力",
        "date":"20201108",
        "content":"右上臂肌肉拉伤\n起初没当回事儿\n现在问题来了\n贴完一盒膏药\n非但没有好转\n连在键盘上\n敲字写诗\n都不太方便\n头一次体会到\n啥叫手无缚鸡之力\n不过\n似乎这个样子\n倒更像个诗人"
    }
]