[
    {
        "title":"双面镜",
        "date":"20210309",
        "content":"妻子用的\n折叠双面镜\n摔坏了一面\n要扔掉\n我说\n“给我带到办公室用”\n“这是女人用的”\n“镜子还分男女吗”\n“你看上面的装饰”\n“没事儿\n我办公室里\n又没其他人”\n“我给你\n另外买一个吧\n别太寒碜了”\n“咱这不是\n变废为宝吗”\n“好吧\n你非得要带去\n我就把上面的装饰\n帮你撕下来\n一个大男人\n用女人的镜子\n想着就不舒服”"
    },
    {
        "title":"双面人",
        "date":"20200406",
        "content":"妻子嘲笑我情商低\n我予以反驳道\n“情商低不好吗\n如果情商高的话\n指不定讨多少女人喜欢\n让你吃醋生闷气呢”\n“你就不能在我面前情商高\n在别的女人面前情商低吗”"
    },
    {
        "title":"水杯盖儿",
        "date":"20200819",
        "content":"会场上\n一个女孩的水杯盖儿\n不小心掉地上了\n她冲邻座女孩\n吐了下舌头\n邻座\n摊开双手\n笑了笑\n是啊\n跟前的条桌\n挡住她俩了\n起身出来捡吧\n得好几个人让道\n坐在最头上的小伙子\n看出了女孩的尴尬\n轻轻走过去\n帮她捡起来了\n哦，一切都悄无声息\n那女孩或许不想\n影响会场秩序\n已在心里面\n给小伙子\n道了声谢谢\n不然\n她咋会长得\n那么好看呢"
    },
    {
        "title":"水滴筹",
        "date":"20210227",
        "content":"二姨子查出\n卵巢癌晚期\n医生诊断为\n一年存活期\n现在不流行\n水滴筹吗\n如果可以\n我来组织发起\n不需要多的\n每个有爱心的人\n只需要捐出你们\n生命中的\n一秒钟"
    },
    {
        "title":"水缸",
        "date":"20210109",
        "content":"说到天气冷\n母亲说\n这哪儿叫冷啊\n记得1954年冬天\n水缸里的水\n都冻成冰坨子\n你舅舅把水缸\n滚到屋外\n放太阳底下晒\n还融化不了\n又抱来\n几捆稻草\n点着了用火烤\n不然\n家里连做饭的水\n都没有"
    },
    {
        "title":"水管破了",
        "date":"20200607",
        "content":"父母门前水管\n被邻居挖破了\n打跟前走过的人\n十有八九\n张扬一声\n“哎呀！\n这儿水管\n怎么破了哟”\n父母坐在门前\n从不应声\n若碰到熟人\n就冲邻居家\n指一指"
    },
    {
        "title":"水果店",
        "date":"20200909",
        "content":"巷子口新开了家\n时尚水果蔬菜店\n每天打跟前\n走过来走过去\n不见一个顾客\n光见俩毛头小子\n一个守在店门口\n一个守在店里\n心说\n这真应了\n那句俗语\n“嘴上无毛\n办事不牢”\n看吧\n一个月后\n俩人指定\n卷铺盖走人\n之所以\n做出如此判断\n只因为这家店\n选址有问题\n开在城中村里"
    },
    {
        "title":"水果过敏",
        "date":"20210424",
        "content":"傍晚\n回父母家\n刚坐下\n母亲就跟我介绍\n父亲一天来的\n饮食情况\n早中晚三餐\n都吃得不少\n上午还吃了\n大半个苹果\n下午又吃了\n半个丑八怪\n忽然想起\n父亲痴呆之前\n几乎不吃水果\n谁要他吃\n就跟谁急\n“不跟你说了吗\n我吃不得水果\n吃了就过敏\n胃痛\n浑身痒”"
    },
    {
        "title":"水果种子",
        "date":"20210224",
        "content":"在自家花盆里\n我曾经埋下过\n各种各样的\n水果种子\n希望它们\n能够长出来\n哦，这些种子\n多像我儿时的\n一个个理想呀\n可它们最终\n都没能冒芽"
    },
    {
        "title":"水饺",
        "date":"20191225",
        "content":"一碗水饺\n吃剩4个\n忽然想起\n以往出游经历\n团餐没啥油水\n无论吃得多饱\n总管不到下顿\n彼时\n要有这么几个水饺\n拿来充饥的话\n哦\n只这么一想\n眼前的水饺\n仿佛添了高汤\n味道那个鲜啊\n啧啧啧"
    },
    {
        "title":"水酒麹",
        "date":"20210615",
        "content":"路过一块芝麻地\n看到初开的\n芝麻花\n不禁想起小时候\n总有意去生产队\n芝麻地割猪草\n趁四下无人之际\n偷采芝麻花回家\n给母亲做水酒麹\n整个夏天\n母亲每天一早起来\n就煮一大盆水酒\n先摊冷\n再用井水镇着\n干完活或放学回来\n每人就能喝上一碗\n解暑"
    },
    {
        "title":"水龙头",
        "date":"20200825",
        "content":"父母邻居老万\n膀胱癌手术后\n小便失禁\n他老伴儿\n只要跟人提起\n就一个劲儿后悔\n“花了几万块呢\n早知道这样\n之前就不做手术了\n好像水龙头坏了样\n越修越不管用\n唉\n索性是个水龙头\n那倒也好\n可以帮他\n再换一个”"
    },
    {
        "title":"水漫金山",
        "date":"20200710",
        "content":"没有参加"
    },
    {
        "title":"水泥地",
        "date":"20210429",
        "content":"一家人\n坐在门前聊天\n大妹说我性格不好\n看起来表面斯文\n实则脾气耿直\n性子刚烈\n宁断不弯\n不够圆滑\n这辈子\n无论走到哪儿\n都是当副职的命\n肯定还吃了\n不少苦头\n母亲指着门前水泥地说\n这水泥地就是因为太硬\n所以要留伸缩缝\n不然\n就是没车碾压\n自己也会破裂"
    },
    {
        "title":"水皮",
        "date":"20201226",
        "content":"晚饭过后\n拿了颗\n盐酸多奈哌齐\n给父亲吃\n估计水温有点儿高\n帮他吹了会儿\n也是我大意了\n没亲口尝一尝\n便直接递给了父亲\n父亲喝了口后说\n“面上一层皮子还好\n下面的水\n有点儿烫”"
    },
    {
        "title":"水扫帚",
        "date":"20210502",
        "content":"一夜大风\n洗车店门前\n香樟树撒下\n厚厚的一层\n落叶和花托\n洗车小哥\n打开店铺\n拿出把水枪\n把地面打扫得\n干干净净"
    },
    {
        "title":"水深火热",
        "date":"20200907",
        "content":"母亲看完新闻联播\n替美国人民着急道\n“又是大火\n又是犯罪\n又是新冠肺炎\n看美国人怎么得了哟”\n母亲要是书再读多点儿\n肯定会说出\n“水深火热”\n这个词"
    },
    {
        "title":"水箱",
        "date":"20200619",
        "content":"父亲上厕所\n半天没尿出来\n尽管我在旁边\n不停地吹口哨\n仍不管用\n没想母亲走进来\n伸手就去摁水箱\n我赶紧阻止\n“还没尿呢”\n“不是冲\n是帮他\n把尿引出来”"
    },
    {
        "title":"水压",
        "date":"20200911",
        "content":"我住的是6楼\n家中水压\n向来不行\n今儿早上\n打开水龙头\n一股清水喷涌而出\n咦\n难道全城的供水管网\n全部更新过了\n再也不怕\n爆管了吗\n到单位\n方才把心中的疑惑解开\n这一片临晨5点\n大面积停水\n正在抢修管道"
    },
    {
        "title":"水也有营养",
        "date":"20191104",
        "content":"妻子把5个空瓶子\n灌满水后\n搁在书房窗台上\n然后在每个瓶子里\n插入1棵吊兰幼苗\n没想一个多月后\n它们都长大了\n这让我想起\n40多年前\n老家村里\n老海一家\n那会儿\n他家孩子多\n是缺粮大户\n他们家人\n每天只吃一顿饭\n肚子饿了就喝水\n可他5个女儿\n个个长得\n白白胖胖的\n社员们都羡慕\n老海火好\n5个女儿\n光喝水\n就养大了"
    }
]