[
    {
        "title":"小淡词：032——长途汽车",
        "date":"201108",
        "content":"几头烂蒜充当主角，烂蒜们凝固血，地上掉落不少空壳\n到处乱摸\n舍\n才能\n得\n虚弱开始工作，生产哆嗦。小脸们不再阳光灿烂\n刀的寒光刺得瞎\n眼。呼喊。迅速耳聋。长途汽车正常运行"
    },
    {
        "title":"小淡词：033——拥抱",
        "date":"201108",
        "content":"夏天时\n两岁的儿子\n和我\n上身赤裸\n我往\n身上刷蜜，儿子往身上洒糖水，然后拥抱。我们的皮肤\n那时是最敏感的味觉器官。浸入不同的甜\n那一刻\n女人\n都滚了\n蛋"
    },
    {
        "title":"小淡词：034——牛乳房",
        "date":"201108",
        "content":"柔软与春困的复方制剂胜过安眠药片\n牛乳房柔软得\n令人担心\n阴狠的掌\n不可能用它练功\n怎忍心\n震碎生产纯洁的\n小工厂\n牛乳房真的开始令人担心\n摸到了硬块\n不由得去看身边心爱的女人"
    },
    {
        "title":"小淡词：035——饺子",
        "date":"201108",
        "content":"向下再向下一直向下，不管是肉丸还是菜馅\n终其一生，完成堕落。被铁锅捕获\n沸水中炼狱，烟火气无限，像捣蒜，世俗就轻易开花\n蒸汽浓情，要不停食下人烟\n刚揭锅，一片膨胀，像我特定时刻的欲望\n但转瞬回落\n向上\n向上\n再向上\n鸟就是鸟云愿意做云"
    },
    {
        "title":"小淡词：036——雾",
        "date":"201108",
        "content":"雾犹豫，不肯散去\n我可以一大杯酒一饮而尽\n一刀剁掉鸡头，周围炊烟四起\n远处种种声音\n和锅里的香气凶猛杀伐过来\n这是初春，有不少探子提前早到\n女人分娩后，难免一时虚弱"
    },
    {
        "title":"小淡词：037——黑子有尊严要性要自由",
        "date":"201108",
        "content":"黑子是我小时家里的狗\n黑子阳光下靠墙根午睡\n搓弄狗，狗矜鼻子呲牙发怒\n现在回想，我碰碎了狗的美梦\n\n大雪天的早上，狗窝旁剩下铁链\n是头天晚上没喂饱狗\n黑子走后获得自由，还有艳遇"
    },
    {
        "title":"小淡词：038——表大爷喝醉",
        "date":"201108",
        "content":"小炕桌钉在炕上，小酒盅一捏\n醉后打老婆\n儿子和爹翻脸，老猫不给他好脸\n老婆被打得到处躲藏\n表大爷寡人一个，酒喝得噎住\n去外省找勘探地质的妹子\n丢了地址，醉着闯进一家胡言乱语\n本地人把他打死，取回来的遗照，表大爷样子很惨"
    },
    {
        "title":"小淡词：039——很容易被囚困",
        "date":"201108",
        "content":"我不是犯人，天地间有很多看上去很自在的人\n到处走走，牢房韧而无形\n且随时随地设立\n被囚住，还有所不知\n我不是犯人，但不是因此就不被关进去"
    },
    {
        "title":"小淡词：040——灯泡",
        "date":"201108",
        "content":"大脑袋的灯泡\n亮了很长时间\n令人担心\n灯泡会不会\n亮碎自己\n\n有颗大脑袋想法很多\n被很多想法鼓胀着\n长此下去\n大脑袋有可能\n裂开\n\n“好了。现在关灯！”\n有着满脑袋想法的\n大脑袋"
    },
    {
        "title":"小淡词：041——柳骨",
        "date":"201111",
        "content":"春天，各种身体都在酿酒\n柳骨从皮里抽出\n柳骨湿润，这是破了身\n春天酿的一种酒的气味开始弥散"
    },
    {
        "title":"小淡词：042——窃听器",
        "date":"201111",
        "content":"放在老婆身上\n老婆和情夫有没有谋害亲夫的\n诡计\n放在小情人身上\n小情人与她的新欢说了我\n哪些坏话\n放在头的家里\n换个捞票子的位置\n头的胃口\n有多大"
    },
    {
        "title":"小淡词：043——像父亲",
        "date":"201111",
        "content":"父亲撸起袖子\n喝小酒\n秃顶上经常冒汗\n酒在口中稍有停顿\n这一小会儿\n父亲的身体里我的身体里在涨潮\n睡下后我旧得像父亲\n潮水正缓慢退去\n醒来后\n父亲在我身体里顽固地做将军"
    },
    {
        "title":"小淡词：044——八角台",
        "date":"201111",
        "content":"那时一个书生过一条河，他不能想象北方以北\n风与野草围在一座土台四周谈笑\n书生柔弱，要被风吹折。站在土台上\n书生会如陈子昂一样吟出：念天地之悠悠"
    },
    {
        "title":"小淡词：045——玉米的疼痛",
        "date":"201111",
        "content":"撕开鲜嫩的玉米皮\n此时有没有感觉到，这好像在\n夜凉如水之时\n剥去一个婴儿的外衣\n玉米身体散发出清香\n香气很淡，月光抚摸一个人的肌肤\n接着薅去柔嫩的玉米须\n此时玉米应该有感觉，这好像是\n惊醒熟睡的婴儿\n然后薅着他的毛发\n玉米没有哭，她哭不出声来"
    },
    {
        "title":"小淡词：046——雨前",
        "date":"201111",
        "content":"云酝酿情绪，飞鸟轻灵飞翔，它们都有\n一场戏剧开场前的心情\n远处传来的声音，格外清晰。\n风动几下，像有幕布在鼓荡\n里面的神秘即将现出"
    },
    {
        "title":"小淡词：047——黄昏沙漠",
        "date":"201111",
        "content":"走在软体动物身上，找不到它的眼\n它的目光像在某处一直注视\n一粒砂极力靠近一粒砂，两粒砂之间还有很多孤独\n黄昏是给软体动物的安眠药，它正慢慢服用"
    },
    {
        "title":"小淡词：048——遗弃",
        "date":"201111",
        "content":"夏天，一枚残留果肉的果核被遗弃。立刻\n围上一群苍蝇或蚂蚁\n它们误以为这是人遗弃的一小块\n不良的良心，它们议论纷纷\n它们对人\n对人丢掉的东西，都感兴趣"
    },
    {
        "title":"小淡词：049——耳光",
        "date":"201111",
        "content":"火车惯性十足\n它有它的方向\n风醉醺醺地，只会胡乱拍击。那些张开的翅膀，偶而掠过\n需要一记耳光\n能震动身体里的火车\n的一记耳光"
    },
    {
        "title":"小淡词：050——籽粒",
        "date":"201111",
        "content":"袋子里，籽粒裸身挤在一起\n没小声议论同一个想法：在哪发芽\n都在一袋子黑暗里酝酿情绪\n老鼠后来睡着了，也没说出"
    },
    {
        "title":"小淡词：051——夜晚的孤独",
        "date":"201202",
        "content":"孤独在夜晚开花，是黑颜色的花\n夜晚有吸不完的黑暗\n孤独大朵开放，放肆地打开身体"
    }
]