[
    {
        "title":"与父书",
        "date":"",
        "content":"父亲，你以草木的方式\n继续生长着。而我也以你曾经\n有过的样子在风雨中行走\n不得不承认，我始终跟不上你\n成长的速度。某一天\n当我怀抱一颗小草之心\n慢慢靠近你，你又会以参天大树\n的姿态，迎接我的抵达"
    },
    {
        "title":"这样的时刻",
        "date":"",
        "content":"时钟在停止的时刻\n最准确\n像弥留之际的善念\n\n大地在丰收之后\n最荒凉\n像我们曾经深爱\n\n镜子在无人的间隙\n最静寂\n像你悄然离开\n\n灯光在子夜时分\n最明澈\n像你读我的眼神\n\n大雪纷飞冬季\n最美丽\n像我们蓦然初见"
    },
    {
        "title":"自然保护区",
        "date":"",
        "content":"在那所空房间里，我们\n忘记了时间\n被生活揉成的褶皱重新回到\n长满青草的床单\n\n她脸上的朝霞，也是晚霞\n世界在上升、塌陷的宿命中\n回旋，好像她起伏不定的\n胸脯和悲欣\n\n我要他吗？她喃喃自语\n精液射出也是一种苦涩的分娩\n我止住她的欲言又止\n——就在瞬息，我们互有所失\n\n光从天窗透射而下\n照着空房间，复照在床第\n流水澄澈，倦鸟憩栖\n飞吧，床单是我们最后的湿地"
    }
]