[
    {
        "title":"梵谷",
        "date":"20150618",
        "content":"描绘孤独的颜料已缺乏\n忧郁\n开始为自己上色…\n\n让不安的线条滑行你内心恐惧\n让蕈黑的天空和你一起瘀伤\n当艺评家的笔已跛脚\n收藏家审美之眼逐渐失明\n文生！\n世界未清明\n请严格遵守你的不如意\n纵使贫困一再敲门\n疾病于你体内扎营\n爱情供应着痛苦\n争执扯断了友谊\n文生！\n请继续追求你的艺术、\n疯狂；以及\n——一生落魄"
    },
    {
        "title":"废墟",
        "date":"20150618",
        "content":"日日夜夜以思念堆砌\n仍扶不起情感断砖碎瓦\n\n岁月斑剥\n残垣的恋情\n不过是座落心头的哀伤建筑"
    },
    {
        "title":"海",
        "date":"20150618",
        "content":"起落的涛波心情想上岸\n起落的涛波心情\n也想退潮"
    },
    {
        "title":"河",
        "date":"20150618",
        "content":"流浪的日子\n有太多哽咽\n如你潜藏汹涌之悒郁\n而水的语言\n人类是不懂的\n愁绪若难消\n当蓄满漂泊心事\n至远方再\n说 与 海 听"
    },
    {
        "title":"湖",
        "date":"20150618",
        "content":"受浊之心\n有澄清的欲望\n风传闻\n所有的树皆笑落了叶"
    },
    {
        "title":"瀑布",
        "date":"20150618",
        "content":"汇聚万种心情\n于山里哭泣\n一洒\n千行眼泪都掉了下来"
    },
    {
        "title":"蛇行的岁月",
        "date":"20150618",
        "content":"蛇行的岁月\n生活过得弯弯曲曲\n欢乐\n倏忽\n一闪即逝\n\n那年少青涩的恋情\n怕生\n已溜进时间的草丛里\n无影无踪"
    },
    {
        "title":"温泉",
        "date":"20150618",
        "content":"大地发烧\n莫名的将我沸腾起来\n让我滚烫易怒的性情\n常常冒烟"
    },
    {
        "title":"诱拐你成一首诗",
        "date":"20150618",
        "content":"相遇的季节\n你脸上盛开着一朵羞赧的笑容\n偷偷地用双眼我轻轻采摘\n采摘你的纯真\n采摘你的无邪\n\n唉！采摘来的美\n可以置于岁月的竹篮里吗？\n\n让三月的风\n撩起你情感的裙䙓\n或用春天的手\n轻抚你柔嫩的心灵\n再缓缓地诱拐你\n诱拐你成一首诗"
    },
    {
        "title":"雨",
        "date":"20150618",
        "content":"堕落之后\n路上洼地\n躺成一张张液体式颓废的脸"
    }
]