[
    {
        "n":"蔡淳祐",
        "p":"caichunyou",
        "c":2,
        "w":198,
        "dw":110
    },
    {
        "n":"蔡方华",
        "p":"caifanghua",
        "c":1,
        "w":105,
        "dw":79
    },
    {
        "n":"蔡富澧",
        "p":"caifuli",
        "c":9,
        "w":3465,
        "dw":1031
    },
    {
        "n":"蔡恒平",
        "p":"caihengping",
        "c":1,
        "w":247,
        "dw":139
    },
    {
        "n":"蔡凯文",
        "p":"caikaiwen",
        "c":1,
        "w":399,
        "dw":231
    },
    {
        "n":"蔡琳森",
        "p":"cailinsen",
        "c":9,
        "w":4199,
        "dw":1295
    },
    {
        "n":"蔡丽双",
        "p":"cailishuang",
        "c":3,
        "w":128,
        "dw":100
    },
    {
        "n":"蔡宁",
        "p":"caining",
        "c":75,
        "w":6695,
        "dw":1544
    },
    {
        "n":"蔡其矫",
        "p":"caiqijiao",
        "c":11,
        "w":1628,
        "dw":653
    },
    {
        "n":"蔡仁伟",
        "p":"cairenwei",
        "c":11,
        "w":1028,
        "dw":441
    },
    {
        "n":"蔡仁仪",
        "p":"cairenyi",
        "c":1,
        "w":584,
        "dw":343
    },
    {
        "n":"蔡荣勇",
        "p":"cairongyong",
        "c":1,
        "w":82,
        "dw":63
    },
    {
        "n":"蔡书清",
        "p":"caishuqing",
        "c":1,
        "w":130,
        "dw":96
    },
    {
        "n":"蔡天新",
        "p":"caitianxin",
        "c":21,
        "w":2298,
        "dw":870
    },
    {
        "n":"蔡宛璇",
        "p":"caiwanxuan",
        "c":1,
        "w":209,
        "dw":128
    },
    {
        "n":"蔡仙",
        "p":"caixian",
        "c":22,
        "w":948,
        "dw":374
    },
    {
        "n":"蔡小敏",
        "p":"caixiaomin",
        "c":19,
        "w":2288,
        "dw":771
    },
    {
        "n":"蔡信义",
        "p":"caixinyi",
        "c":4,
        "w":642,
        "dw":345
    },
    {
        "n":"蔡英明",
        "p":"caiyingming",
        "c":13,
        "w":2298,
        "dw":705
    },
    {
        "n":"彩羽",
        "p":"caiyu",
        "c":9,
        "w":2198,
        "dw":690
    },
    {
        "n":"蔡雨扬",
        "p":"caiyuyang",
        "c":1,
        "w":165,
        "dw":131
    },
    {
        "n":"残笛",
        "p":"candi",
        "c":1,
        "w":134,
        "dw":98
    },
    {
        "n":"苍虞",
        "p":"cangyu",
        "c":6,
        "w":1039,
        "dw":450
    },
    {
        "n":"残墨染",
        "p":"canmoran",
        "c":2,
        "w":114,
        "dw":73
    },
    {
        "n":"残云",
        "p":"canyun",
        "c":3,
        "w":629,
        "dw":324
    },
    {
        "n":"曹葆华",
        "p":"caobaohua",
        "c":1,
        "w":280,
        "dw":176
    },
    {
        "n":"曹兵",
        "p":"caobing",
        "c":8,
        "w":1484,
        "dw":510
    },
    {
        "n":"曹东",
        "p":"caodong",
        "c":50,
        "w":4020,
        "dw":985
    },
    {
        "n":"曹贺林",
        "p":"caohelin",
        "c":8,
        "w":1774,
        "dw":633
    },
    {
        "n":"草花园子",
        "p":"caohuayuanzi",
        "c":1,
        "w":79,
        "dw":63
    },
    {
        "n":"曹开",
        "p":"caokai",
        "c":1,
        "w":205,
        "dw":111
    },
    {
        "n":"曹麓塬",
        "p":"caoluyuan",
        "c":3,
        "w":244,
        "dw":156
    },
    {
        "n":"曹尼",
        "p":"caoni",
        "c":4,
        "w":649,
        "dw":403
    },
    {
        "n":"曹僧",
        "p":"caoseng",
        "c":4,
        "w":831,
        "dw":392
    },
    {
        "n":"曹谁",
        "p":"caoshei",
        "c":26,
        "w":5046,
        "dw":1001
    },
    {
        "n":"草树",
        "p":"caoshu",
        "c":21,
        "w":15020,
        "dw":1990
    },
    {
        "n":"曹疏影",
        "p":"caoshuying",
        "c":26,
        "w":6096,
        "dw":1256
    },
    {
        "n":"曹树莹",
        "p":"caoshuying",
        "c":7,
        "w":11370,
        "dw":1723
    },
    {
        "n":"曹天",
        "p":"caotian",
        "c":16,
        "w":5435,
        "dw":1283
    },
    {
        "n":"曹五木",
        "p":"caowumu",
        "c":1,
        "w":222,
        "dw":115
    },
    {
        "n":"草馨儿",
        "p":"caoxiner",
        "c":74,
        "w":9176,
        "dw":1452
    },
    {
        "n":"曹驭博",
        "p":"caoyubo",
        "c":8,
        "w":2230,
        "dw":739
    },
    {
        "n":"曹宇翔",
        "p":"caoyuxiang",
        "c":21,
        "w":11084,
        "dw":1765
    },
    {
        "n":"曹臻一",
        "p":"caozhenyi",
        "c":1,
        "w":74,
        "dw":52
    },
    {
        "n":"曹忠胜",
        "p":"caozhongsheng",
        "c":25,
        "w":3636,
        "dw":1004
    },
    {
        "n":"cc",
        "p":"cc",
        "c":15,
        "w":1856,
        "dw":710
    },
    {
        "n":"岑灿",
        "p":"cencan",
        "c":1,
        "w":305,
        "dw":126
    },
    {
        "n":"查干",
        "p":"chagan",
        "c":8,
        "w":859,
        "dw":408
    },
    {
        "n":"查干牧仁",
        "p":"chaganmuren",
        "c":53,
        "w":5355,
        "dw":1149
    },
    {
        "n":"柴安平",
        "p":"chaianping",
        "c":1,
        "w":163,
        "dw":90
    },
    {
        "n":"柴柏松",
        "p":"chaibaisong",
        "c":1,
        "w":553,
        "dw":297
    },
    {
        "n":"柴画",
        "p":"chaihua",
        "c":47,
        "w":16652,
        "dw":1996
    },
    {
        "n":"柴然",
        "p":"chairan",
        "c":20,
        "w":7041,
        "dw":1546
    },
    {
        "n":"查理",
        "p":"chali",
        "c":21,
        "w":7697,
        "dw":1507
    },
    {
        "n":"长安瘦马",
        "p":"changanshouma",
        "c":132,
        "w":18168,
        "dw":1959
    },
    {
        "n":"常白",
        "p":"changbai",
        "c":3,
        "w":202,
        "dw":138
    },
    {
        "n":"长短",
        "p":"changduan",
        "c":1,
        "w":429,
        "dw":197
    },
    {
        "n":"长空",
        "p":"changkong",
        "c":1,
        "w":316,
        "dw":185
    },
    {
        "n":"昌耀",
        "p":"changyao",
        "c":35,
        "w":10860,
        "dw":1952
    },
    {
        "n":"昌政",
        "p":"changzheng",
        "c":16,
        "w":2020,
        "dw":729
    },
    {
        "n":"朝格图",
        "p":"chaogetu",
        "c":10,
        "w":1528,
        "dw":668
    },
    {
        "n":"朝颜",
        "p":"chaoyan",
        "c":1,
        "w":193,
        "dw":122
    },
    {
        "n":"茶叶",
        "p":"chaye",
        "c":2,
        "w":381,
        "dw":183
    },
    {
        "n":"车邻",
        "p":"chelin",
        "c":33,
        "w":5918,
        "dw":1394
    },
    {
        "n":"chemrandd",
        "p":"chemrandd",
        "c":1,
        "w":143,
        "dw":116
    },
    {
        "n":"陈安安",
        "p":"chenanan",
        "c":1,
        "w":136,
        "dw":89
    },
    {
        "n":"陈啊妮",
        "p":"chenani",
        "c":14,
        "w":2054,
        "dw":753
    },
    {
        "n":"陈柏伶",
        "p":"chenbailing",
        "c":1,
        "w":149,
        "dw":58
    },
    {
        "n":"陈柏言",
        "p":"chenbaiyan",
        "c":1,
        "w":279,
        "dw":176
    },
    {
        "n":"陈昌远",
        "p":"chenchangyuan",
        "c":6,
        "w":2005,
        "dw":631
    },
    {
        "n":"陈超",
        "p":"chenchao",
        "c":23,
        "w":7067,
        "dw":1584
    },
    {
        "n":"陈晨",
        "p":"chenchen",
        "c":63,
        "w":22185,
        "dw":2193
    },
    {
        "n":"陈陈相因",
        "p":"chenchenxiangyin",
        "c":28,
        "w":9286,
        "dw":2077
    },
    {
        "n":"陈迟恩",
        "p":"chenchien",
        "c":21,
        "w":4506,
        "dw":1152
    },
    {
        "n":"陈大为",
        "p":"chendawei",
        "c":41,
        "w":17700,
        "dw":2328
    },
    {
        "n":"陈大中",
        "p":"chendazhong",
        "c":4,
        "w":1086,
        "dw":430
    },
    {
        "n":"陈德锦",
        "p":"chendejin",
        "c":12,
        "w":2705,
        "dw":885
    },
    {
        "n":"陈东东",
        "p":"chendongdong",
        "c":59,
        "w":20803,
        "dw":2154
    },
    {
        "n":"陈繁齐",
        "p":"chenfanqi",
        "c":6,
        "w":871,
        "dw":334
    },
    {
        "n":"陈斐雯",
        "p":"chenfeiwen",
        "c":20,
        "w":2505,
        "dw":752
    },
    {
        "n":"程碧",
        "p":"chengbi",
        "c":5,
        "w":310,
        "dw":179
    },
    {
        "n":"程沧海",
        "p":"chengcanghai",
        "c":8,
        "w":1011,
        "dw":440
    },
    {
        "n":"沉戈",
        "p":"chenge",
        "c":13,
        "w":1669,
        "dw":533
    },
    {
        "n":"陈舸",
        "p":"chenge",
        "c":2,
        "w":246,
        "dw":152
    },
    {
        "n":"陈革非",
        "p":"chengefei",
        "c":10,
        "w":1078,
        "dw":464
    },
    {
        "n":"陈耿雄",
        "p":"chengengxiong",
        "c":31,
        "w":3483,
        "dw":1084
    },
    {
        "n":"成郭",
        "p":"chengguo",
        "c":3,
        "w":2402,
        "dw":622
    },
    {
        "n":"成果",
        "p":"chengguo",
        "c":10,
        "w":1647,
        "dw":578
    },
    {
        "n":"成路",
        "p":"chenglu",
        "c":42,
        "w":9214,
        "dw":1581
    },
    {
        "n":"成明",
        "p":"chengming",
        "c":124,
        "w":28620,
        "dw":2163
    },
    {
        "n":"程庆莲",
        "p":"chengqinglian",
        "c":99,
        "w":2889,
        "dw":797
    },
    {
        "n":"程世平",
        "p":"chengshiping",
        "c":10,
        "w":1017,
        "dw":488
    },
    {
        "n":"陈广德",
        "p":"chenguangde",
        "c":10,
        "w":1250,
        "dw":510
    },
    {
        "n":"程维",
        "p":"chengwei",
        "c":61,
        "w":16991,
        "dw":2026
    },
    {
        "n":"成向阳",
        "p":"chengxiangyang",
        "c":24,
        "w":4140,
        "dw":1072
    },
    {
        "n":"程小蓓",
        "p":"chengxiaobei",
        "c":14,
        "w":2656,
        "dw":778
    },
    {
        "n":"程歆淳",
        "p":"chengxinchun",
        "c":1,
        "w":166,
        "dw":131
    },
    {
        "n":"成婴",
        "p":"chengying",
        "c":1,
        "w":210,
        "dw":142
    },
    {
        "n":"程玉宇",
        "p":"chengyuyu",
        "c":6,
        "w":1262,
        "dw":522
    },
    {
        "n":"程志强",
        "p":"chengzhiqiang",
        "c":97,
        "w":43800,
        "dw":2841
    },
    {
        "n":"陈汉江",
        "p":"chenhanjiang",
        "c":7,
        "w":4538,
        "dw":1190
    },
    {
        "n":"陈瀚乙",
        "p":"chenhanyi",
        "c":1,
        "w":28,
        "dw":20
    },
    {
        "n":"陈颢仁",
        "p":"chenhaoren",
        "c":1,
        "w":386,
        "dw":250
    },
    {
        "n":"沉河",
        "p":"chenhe",
        "c":186,
        "w":31672,
        "dw":2044
    },
    {
        "n":"陈鸿森",
        "p":"chenhongsen",
        "c":58,
        "w":13586,
        "dw":1742
    },
    {
        "n":"陈煌",
        "p":"chenhuang",
        "c":2,
        "w":98,
        "dw":68
    },
    {
        "n":"陈惠芳",
        "p":"chenhuifang",
        "c":2,
        "w":576,
        "dw":302
    },
    {
        "n":"陈慧桦",
        "p":"chenhuihua",
        "c":12,
        "w":2891,
        "dw":924
    },
    {
        "n":"陈慧遐",
        "p":"chenhuixia",
        "c":29,
        "w":3734,
        "dw":1047
    },
    {
        "n":"陈家带",
        "p":"chenjiadai",
        "c":1,
        "w":570,
        "dw":309
    },
    {
        "n":"陈建",
        "p":"chenjian",
        "c":17,
        "w":3248,
        "dw":962
    },
    {
        "n":"陈江帆",
        "p":"chenjiangfan",
        "c":4,
        "w":426,
        "dw":217
    },
    {
        "n":"陈建男",
        "p":"chenjiannan",
        "c":22,
        "w":5192,
        "dw":1323
    },
    {
        "n":"陈家坪",
        "p":"chenjiaping",
        "c":38,
        "w":13709,
        "dw":1717
    },
    {
        "n":"陈家忠",
        "p":"chenjiazhong",
        "c":10,
        "w":2120,
        "dw":722
    },
    {
        "n":"陈锦标",
        "p":"chenjinbiao",
        "c":6,
        "w":848,
        "dw":339
    },
    {
        "n":"陈镜",
        "p":"chenjing",
        "c":20,
        "w":1172,
        "dw":488
    },
    {
        "n":"陈敬容",
        "p":"chenjingrong",
        "c":16,
        "w":2633,
        "dw":744
    },
    {
        "n":"陈隽弘",
        "p":"chenjuanhong",
        "c":38,
        "w":6288,
        "dw":1253
    },
    {
        "n":"陈骏逸",
        "p":"chenjunyi",
        "c":1,
        "w":111,
        "dw":92
    },
    {
        "n":"陈克",
        "p":"chenke",
        "c":12,
        "w":1798,
        "dw":699
    },
    {
        "n":"陈克华",
        "p":"chenkehua",
        "c":189,
        "w":36032,
        "dw":2707
    },
    {
        "n":"陈可抒",
        "p":"chenkeshu",
        "c":2,
        "w":284,
        "dw":175
    },
    {
        "n":"陈黎",
        "p":"chenli",
        "c":31,
        "w":9978,
        "dw":1701
    },
    {
        "n":"陈令洋",
        "p":"chenlingyang",
        "c":1,
        "w":530,
        "dw":215
    },
    {
        "n":"陈律",
        "p":"chenlv",
        "c":172,
        "w":26461,
        "dw":2224
    },
    {
        "n":"陈美玲",
        "p":"chenmeiling",
        "c":1,
        "w":386,
        "dw":228
    },
    {
        "n":"陈梦家",
        "p":"chenmengjia",
        "c":18,
        "w":3168,
        "dw":785
    },
    {
        "n":"陈铭华",
        "p":"chenminghua",
        "c":11,
        "w":673,
        "dw":397
    },
    {
        "n":"陈明克",
        "p":"chenmingke",
        "c":13,
        "w":3314,
        "dw":874
    },
    {
        "n":"陈明秋",
        "p":"chenmingqiu",
        "c":19,
        "w":3999,
        "dw":1147
    },
    {
        "n":"陈铭尧",
        "p":"chenmingyao",
        "c":4,
        "w":403,
        "dw":250
    },
    {
        "n":"陈敏娟",
        "p":"chenminjuan",
        "c":2,
        "w":136,
        "dw":99
    },
    {
        "n":"沉默的诗者",
        "p":"chenmodeshizhe",
        "c":3,
        "w":549,
        "dw":290
    },
    {
        "n":"陈牧宏",
        "p":"chenmuhong",
        "c":4,
        "w":691,
        "dw":393
    },
    {
        "n":"陈年喜",
        "p":"chennianxi",
        "c":20,
        "w":3766,
        "dw":900
    },
    {
        "n":"陈宁贵",
        "p":"chenninggui",
        "c":4,
        "w":954,
        "dw":472
    },
    {
        "n":"陈沛琪",
        "p":"chenpeiqi",
        "c":7,
        "w":1769,
        "dw":759
    },
    {
        "n":"陈品婕",
        "p":"chenpinjie",
        "c":1,
        "w":411,
        "dw":243
    },
    {
        "n":"陈谦",
        "p":"chenqian",
        "c":5,
        "w":1130,
        "dw":524
    },
    {
        "n":"陈强华",
        "p":"chenqianghua",
        "c":88,
        "w":20428,
        "dw":2233
    },
    {
        "n":"陈千武",
        "p":"chenqianwu",
        "c":76,
        "w":18391,
        "dw":2190
    },
    {
        "n":"陈庆",
        "p":"chenqing",
        "c":2,
        "w":180,
        "dw":124
    },
    {
        "n":"陈全德",
        "p":"chenquande",
        "c":19,
        "w":967,
        "dw":443
    },
    {
        "n":"陈让",
        "p":"chenrang",
        "c":6,
        "w":992,
        "dw":386
    },
    {
        "n":"陈人杰",
        "p":"chenrenjie",
        "c":12,
        "w":1138,
        "dw":572
    },
    {
        "n":"陈仁凯",
        "p":"chenrenkai",
        "c":103,
        "w":13844,
        "dw":1954
    },
    {
        "n":"陈日玚",
        "p":"chenrichang",
        "c":1,
        "w":237,
        "dw":134
    },
    {
        "n":"陈瑞",
        "p":"chenrui",
        "c":20,
        "w":5519,
        "dw":1201
    },
    {
        "n":"陈三九",
        "p":"chensanjiu",
        "c":13,
        "w":2167,
        "dw":722
    },
    {
        "n":"陈少",
        "p":"chenshao",
        "c":5,
        "w":1302,
        "dw":642
    },
    {
        "n":"陈韶辉",
        "p":"chenshaohui",
        "c":11,
        "w":2312,
        "dw":790
    },
    {
        "n":"陈傻子",
        "p":"chenshazi",
        "c":38,
        "w":2760,
        "dw":646
    },
    {
        "n":"陈十八",
        "p":"chenshiba",
        "c":27,
        "w":1705,
        "dw":582
    },
    {
        "n":"陈诗哥",
        "p":"chenshige",
        "c":50,
        "w":9182,
        "dw":1424
    },
    {
        "n":"陈树照",
        "p":"chenshuzhao",
        "c":48,
        "w":5493,
        "dw":1167
    },
    {
        "n":"陈思楷",
        "p":"chensikai",
        "c":6,
        "w":1219,
        "dw":540
    },
    {
        "n":"陈思娴",
        "p":"chensixian",
        "c":8,
        "w":3695,
        "dw":1256
    },
    {
        "n":"陈甜甜",
        "p":"chentiantian",
        "c":1,
        "w":76,
        "dw":51
    },
    {
        "n":"陈天雄",
        "p":"chentianxiong",
        "c":15,
        "w":3302,
        "dw":890
    },
    {
        "n":"陈婷",
        "p":"chenting",
        "c":5,
        "w":763,
        "dw":372
    },
    {
        "n":"陈危",
        "p":"chenwei",
        "c":1,
        "w":986,
        "dw":503
    },
    {
        "n":"陈炜潘",
        "p":"chenweipan",
        "c":111,
        "w":27644,
        "dw":2078
    },
    {
        "n":"陈文辉",
        "p":"chenwenhui",
        "c":11,
        "w":1759,
        "dw":649
    },
    {
        "n":"陈汐",
        "p":"chenxi",
        "c":2,
        "w":431,
        "dw":226
    },
    {
        "n":"陈先发",
        "p":"chenxianfa",
        "c":278,
        "w":73856,
        "dw":3140
    },
    {
        "n":"陈翔",
        "p":"chenxiang",
        "c":28,
        "w":7900,
        "dw":1385
    },
    {
        "n":"陈肖",
        "p":"chenxiao",
        "c":49,
        "w":11000,
        "dw":1682
    },
    {
        "n":"陈小平",
        "p":"chenxiaoping",
        "c":8,
        "w":1272,
        "dw":546
    },
    {
        "n":"陈星光",
        "p":"chenxingguang",
        "c":95,
        "w":12964,
        "dw":1829
    },
    {
        "n":"陈秀喜",
        "p":"chenxiuxi",
        "c":79,
        "w":12550,
        "dw":1887
    },
    {
        "n":"陈颜",
        "p":"chenyan",
        "c":3,
        "w":316,
        "dw":190
    },
    {
        "n":"陈衍强",
        "p":"chenyanqiang",
        "c":210,
        "w":38546,
        "dw":2426
    },
    {
        "n":"陈延祯",
        "p":"chenyanzhen",
        "c":4,
        "w":1369,
        "dw":579
    },
    {
        "n":"陈耀宗",
        "p":"chenyaozong",
        "c":14,
        "w":3465,
        "dw":1106
    },
    {
        "n":"陈雅雯",
        "p":"chenyawen",
        "c":2,
        "w":237,
        "dw":145
    },
    {
        "n":"陈怡安",
        "p":"chenyian",
        "c":1,
        "w":123,
        "dw":85
    },
    {
        "n":"陈易聪",
        "p":"chenyicong",
        "c":1,
        "w":273,
        "dw":174
    },
    {
        "n":"陈依达",
        "p":"chenyida",
        "c":2,
        "w":1062,
        "dw":551
    },
    {
        "n":"陈懿范",
        "p":"chenyifan",
        "c":1,
        "w":138,
        "dw":99
    },
    {
        "n":"陈怡瑾",
        "p":"chenyijin",
        "c":3,
        "w":569,
        "dw":352
    },
    {
        "n":"陈滢州",
        "p":"chenyingzhou",
        "c":2,
        "w":485,
        "dw":289
    },
    {
        "n":"陈依文",
        "p":"chenyiwen",
        "c":4,
        "w":645,
        "dw":378
    },
    {
        "n":"陈乙新",
        "p":"chenyixin",
        "c":2,
        "w":227,
        "dw":167
    },
    {
        "n":"陈义芝",
        "p":"chenyizhi",
        "c":56,
        "w":10705,
        "dw":1820
    },
    {
        "n":"陈勇",
        "p":"chenyong",
        "c":25,
        "w":6784,
        "dw":1520
    },
    {
        "n":"陈佑嘉",
        "p":"chenyoujia",
        "c":1,
        "w":110,
        "dw":68
    },
    {
        "n":"陈鱼",
        "p":"chenyu",
        "c":4,
        "w":2496,
        "dw":744
    },
    {
        "n":"陈跃军",
        "p":"chenyuejun",
        "c":10,
        "w":1697,
        "dw":578
    },
    {
        "n":"陈育虹",
        "p":"chenyuhong",
        "c":5,
        "w":987,
        "dw":346
    },
    {
        "n":"陈煜佳",
        "p":"chenyujia",
        "c":57,
        "w":9397,
        "dw":1504
    },
    {
        "n":"陈玉玲",
        "p":"chenyuling",
        "c":1,
        "w":214,
        "dw":137
    },
    {
        "n":"陈玉伦",
        "p":"chenyulun",
        "c":10,
        "w":2027,
        "dw":726
    },
    {
        "n":"陈云虎",
        "p":"chenyunhu",
        "c":10,
        "w":1320,
        "dw":440
    },
    {
        "n":"陈允元",
        "p":"chenyunyuan",
        "c":2,
        "w":256,
        "dw":158
    },
    {
        "n":"陈钰鹏",
        "p":"chenyupeng",
        "c":3,
        "w":932,
        "dw":419
    },
    {
        "n":"陈昱文",
        "p":"chenyuwen",
        "c":1,
        "w":52,
        "dw":40
    },
    {
        "n":"陈育萱",
        "p":"chenyuxuan",
        "c":1,
        "w":125,
        "dw":100
    },
    {
        "n":"陈昭渊",
        "p":"chenzhaoyuan",
        "c":6,
        "w":654,
        "dw":365
    },
    {
        "n":"陈子谦",
        "p":"chenziqian",
        "c":1,
        "w":213,
        "dw":150
    },
    {
        "n":"陈宗华",
        "p":"chenzonghua",
        "c":396,
        "w":39847,
        "dw":2964
    },
    {
        "n":"陈作二",
        "p":"chenzuoer",
        "c":9,
        "w":1143,
        "dw":464
    },
    {
        "n":"车前子",
        "p":"cheqianzi",
        "c":13,
        "w":2655,
        "dw":853
    },
    {
        "n":"车延高",
        "p":"cheyangao",
        "c":129,
        "w":21923,
        "dw":2182
    },
    {
        "n":"池底",
        "p":"chidi",
        "c":4,
        "w":492,
        "dw":285
    },
    {
        "n":"迟顿",
        "p":"chidun",
        "c":20,
        "w":2364,
        "dw":731
    },
    {
        "n":"迟钝",
        "p":"chidun",
        "c":27,
        "w":7766,
        "dw":1642
    },
    {
        "n":"池儿",
        "p":"chier",
        "c":17,
        "w":2612,
        "dw":877
    },
    {
        "n":"Chiffon",
        "p":"chiffon",
        "c":5,
        "w":1099,
        "dw":519
    },
    {
        "n":"chihta",
        "p":"chihta",
        "c":3,
        "w":851,
        "dw":481
    },
    {
        "n":"池莉",
        "p":"chili",
        "c":1,
        "w":226,
        "dw":125
    },
    {
        "n":"池凌云",
        "p":"chilingyun",
        "c":496,
        "w":97739,
        "dw":2958
    },
    {
        "n":"池沫树",
        "p":"chimoshu",
        "c":22,
        "w":4971,
        "dw":1009
    },
    {
        "n":"虫嗅",
        "p":"chongxiu",
        "c":7,
        "w":2070,
        "dw":728
    },
    {
        "n":"虫子",
        "p":"chongzi",
        "c":1,
        "w":59,
        "dw":51
    },
    {
        "n":"丑石",
        "p":"choushi",
        "c":428,
        "w":46627,
        "dw":2425
    },
    {
        "n":"丑乙",
        "p":"chouyi",
        "c":5,
        "w":799,
        "dw":364
    },
    {
        "n":"楚阿海少",
        "p":"chuahaishao",
        "c":1,
        "w":123,
        "dw":100
    },
    {
        "n":"川美",
        "p":"chuanmei",
        "c":10,
        "w":1912,
        "dw":604
    },
    {
        "n":"初安民",
        "p":"chuanmin",
        "c":3,
        "w":612,
        "dw":301
    },
    {
        "n":"楚尘",
        "p":"chuchen",
        "c":1,
        "w":228,
        "dw":105
    },
    {
        "n":"楚歌",
        "p":"chuge",
        "c":29,
        "w":11173,
        "dw":1560
    },
    {
        "n":"楚狂",
        "p":"chukuang",
        "c":2,
        "w":501,
        "dw":275
    },
    {
        "n":"春树",
        "p":"chunshu",
        "c":18,
        "w":2671,
        "dw":719
    },
    {
        "n":"初秋的驮马",
        "p":"chuqiudetuoma",
        "c":6,
        "w":1775,
        "dw":732
    },
    {
        "n":"churdy",
        "p":"churdy",
        "c":14,
        "w":3983,
        "dw":975
    },
    {
        "n":"楚吴",
        "p":"chuwu",
        "c":8,
        "w":1754,
        "dw":710
    },
    {
        "n":"初相遇",
        "p":"chuxiangyu",
        "c":31,
        "w":7263,
        "dw":1371
    },
    {
        "n":"楚影",
        "p":"chuying",
        "c":4,
        "w":648,
        "dw":348
    },
    {
        "n":"楚雨",
        "p":"chuyu",
        "c":105,
        "w":19721,
        "dw":2244
    },
    {
        "n":"褚岳霖",
        "p":"chuyuelin",
        "c":2,
        "w":377,
        "dw":220
    },
    {
        "n":"Clement",
        "p":"clement",
        "c":3,
        "w":473,
        "dw":287
    },
    {
        "n":"cm",
        "p":"cm",
        "c":3,
        "w":675,
        "dw":270
    },
    {
        "n":"Coffee",
        "p":"coffee",
        "c":1,
        "w":129,
        "dw":95
    },
    {
        "n":"崔剑明",
        "p":"cuijianming",
        "c":9,
        "w":2444,
        "dw":656
    },
    {
        "n":"崔舜华",
        "p":"cuishunhua",
        "c":9,
        "w":2477,
        "dw":922
    },
    {
        "n":"崔树田",
        "p":"cuishutian",
        "c":14,
        "w":2328,
        "dw":863
    },
    {
        "n":"崔万福",
        "p":"cuiwanfu",
        "c":16,
        "w":2104,
        "dw":687
    },
    {
        "n":"崔岩",
        "p":"cuiyan",
        "c":10,
        "w":1782,
        "dw":673
    }
]