[
    {
        "title":"伟人和小兔子",
        "date":"20000820",
        "content":"伟人和我喂养的小兔子\n死在同一个晚上\n\n天蒙蒙亮时\n我把小兔子扔进垃圾堆\n随后在报纸上\n看到了伟人的遗照\n\n伟人干干净净\n死后也化成干干净净的灰\n而过不了多久\n我的小兔子\n就会散发出冲天臭气\n让人们都捂起鼻子\n\n一种复仇的快感\n在我心中油然升起"
    },
    {
        "title":"我所认识的乡村",
        "date":"",
        "content":"我所认识的乡村\n和诗人讴歌的不同\n我所认识的乡村\n不愿再做贞洁坊\n养活一群精神阳痿的人\n我所认识的乡村\n是正在丰满的身体\n渴望城市的抚摸\n哪怕那双手\n有点肮脏"
    },
    {
        "title":"无题",
        "date":"",
        "content":"我从《人民日报》上\n找性病广告\n我相信刊于此报的\n定是最权威的\n我用雷达般的眼睛\n把整张报纸仔仔细细\n搜寻了三遍\n却压根儿没有\n性病广告的影子\n倒有一整版\n关于某战斗机的介绍\n战斗机是个好东西\n只是我暂时\n还用不着"
    },
    {
        "title":"雨过天晴",
        "date":"20000817",
        "content":"雨过天晴\n城市干净极了\n就像刚冲洗过的厕所\n一样干净\n人们又走了出来\n他们又可以舒舒服服地\n方便上一阵子了"
    },
    {
        "title":"致怀古的诗人们",
        "date":"20000817",
        "content":"怀古的诗人\n洞房准备好了吗\n看！马王堆的千年女尸\n已坐上了花轿"
    }
]