[
    {
        "title":"暮春之初",
        "date":"",
        "content":"叫不上名字的鸟\n叫不上名字的草\n那只鸟的叫声仿佛一串质地好的珍珠\n而那蓬草开的花则太细小和琐碎。如米之小"
    },
    {
        "title":"木芙蓉",
        "date":"",
        "content":"我想在我的院子里\n栽下一棵木芙蓉\n写下这句诗的时候\n木芙蓉在我的院子里\n已经开始生长\n相信它一定经冬不凋\n而且高贵\n而且放荡\n虽然，至今我不知道\n木芙蓉是怎样一种花"
    },
    {
        "title":"那样单薄的树却有那样精致的叶子",
        "date":"",
        "content":"窗外，一株单薄的树\n另外三五株，同样单薄\n那样单薄的树却有那样精致的叶子\n扇形的叶子，金黄的叶子\n脉络清晰，轮廓分明\n像极了这里的人，清贫却也清高"
    },
    {
        "title":"廿年以来",
        "date":"20070427",
        "content":"廿年以来\n我执教某所中学\n一贯的勤谨和缓\n成百上千的鲤鱼\n从我这里一跃而跳过了龙门\n其中有俗人理解不了的幸福\n其中有庸人感受不到的孤独和寂寞\n幸福也是我一人\n孤独也是我一人\n寂寞也是我一人\n廿年以来，独自一人\n我在修持着我的这种枯禅\n平生志业尽在此\n敢不宵衣又旰食\n几分孤独一般独自吞了\n几分寂寞一般独自咽了\n一分幸福也一般独自在受用\n青灯黄卷，晨钟暮鼓\n廿年以来我像一个高僧一样\n勇猛精进"
    },
    {
        "title":"偶尔会有大鸟落在旗杆上",
        "date":"",
        "content":"这里是高三\n老师忙\n学生忙\n校园大多数时间显得空空荡荡\n寂静的校园\n偶尔会有大鸟落在旗杆上\n匆匆忙忙的人们无暇顾及\n鸟\n悠闲\n而\n落寞"
    },
    {
        "title":"上帝的灯盏",
        "date":"20041207",
        "content":"裸穗斟满了酒。我和人邻各干了一个。\n桂晔用手机给我们照明。我深一脚，浅一脚。\n山下万家灯火。我心中有一盏灯明亮盛过辉煌的万家灯火，\n无以名之，且曰上帝的灯盏。"
    },
    {
        "title":"上元节，镇日昏睡。向晚而作",
        "date":"20050223",
        "content":"人，给你\n灯，给你\n月，给你\n只是，把那平安给我。何如？"
    },
    {
        "title":"深夜，会传来恶犬的狂吠声",
        "date":"",
        "content":"二十二点五十分\n第三节晚自习下后\n校园彻底安静下来\n一切都仿佛进入了梦乡\n非常大气的教学楼恐怕也进入了它优雅的梦乡\n空旷无比的操场肯定同时踏入了它安逸的梦乡\n夜间值班的我安顿身心也正准备进入我的梦乡\n这时，远处传来恶犬的狂吠声\n“悦纳一切”，仿佛一个声音轻轻说"
    },
    {
        "title":"诗意之一种",
        "date":"",
        "content":"家住廉租房\n大人们\n卧病在床\n孩子们\n奖状满墙"
    },
    {
        "title":"时代",
        "date":"20070328",
        "content":"你预定的书到了\n我预定的书到了\n放下电话\n侧身而起\n取我的书\n轻轻地我去了\n数一数几个小钱\n带来了我的书\n这样的情形多了\n我也有了一点点思考\n这是时代之恩赐呀\n我要感谢这惟利是图的时代\n几个小钱\n就让我和时代接轨了\n几个小钱\n就让我和世界接轨了"
    },
    {
        "title":"太平洋也不过一洼之水",
        "date":"",
        "content":"我是现实中的玄奘\n你是传说中的观音\n我是中国\n你是美国\n我们是一本书\n我是封面\n你是封底\n但是啊现实却是，我们\n分房而睡\n分餐而食\n即使如此\n我也坚信\n菩萨在山上\n玄奘在路上\n太平洋也不过一洼之水"
    },
    {
        "title":"太统山庄一日游",
        "date":"20070507",
        "content":"不期而遇遇到的\n依然是日常的动物\n牛甚至驴\n传说中的豹子\n并未现身\n不期而至听到的\n依然是平常的鸟语\n一声甚至数声\n传说中的鹰隼\n也并未出现\n纷至沓来的人啊\n出乎预料快乐并且闲散\n徜徉在人群中的那个叫独化的人\n他的快乐是那传说中猛兽的快乐\n他的闲散也是传说中猛禽的闲散"
    },
    {
        "title":"同门",
        "date":"20150617",
        "content":"十五志学\n三十而立\n同门身影\n遍布全球\n今天，\n孙泽洲从美国回来\n贾皓从北京回来\n陶立从上海回来\n泽洲，讲讲你的硅谷\n贾皓，讲讲你的实验\n陶立，讲讲你的股票\n夜凉如水\n同门讲堂\n刚刚开始\n英语与汉语齐飞\n科技并人文一色\n这是教育的红利\n且让我们分享"
    },
    {
        "title":"为什么？",
        "date":"20050205",
        "content":"一个几乎和我无关的人跳进冰冷的湖水，死了。\n死亡日期：二〇〇五年二月三日（农历腊月二十五）\n死亡方式：皮甲克外衣内衣手机整齐地放置湖边，\n为什么？为什么裤衩背心跳进冰冷的湖水死了呢？"
    },
    {
        "title":"我们",
        "date":"20120115",
        "content":"也曾三更灯\n也曾五更鸡\n鱼化龙，我们\n成为一名光荣的人民教师\n太阳下最光辉的职业\n士农工商，我们别无选择\n我们选择做一个士人\n平生志业尽在此\n敢不宵衣又旰食\n我们放飞希望\n我们留守空巢\n利国利民\n霜染鬓发\n无怨无悔\n甘为人梯\n纵浪大化\n不忧不惧\n十年过去了\n二十年过去了\n三十年过去了\n所有梦想都开花\n滋兰九畹\n树蕙百亩\n一阕新词歌盛世\n满头白发述平生\n看云卷云舒\n听花开花落\n作为一名光荣的人民教师\n我们从容淡定\n我们洒脱刚健\n我们优雅和谐\n我们走在我们内心的金光大道上"
    },
    {
        "title":"我是荷",
        "date":"",
        "content":"为什么？我来到了这里，\n这儿是永恒的黑暗啊。\n我是荷。凭此一念，\n我从这荒凉的世界上站立起来了。"
    },
    {
        "title":"我主持圆通寺一个下午",
        "date":"",
        "content":"它破败\n它空无一人\n我嗅到了我点燃的清香\n我看到了花木上拂过的泠风"
    },
    {
        "title":"无题",
        "date":"",
        "content":"天气这样冷，\n你寄人篱下。\n铅泪，之外\n我什么也没有"
    },
    {
        "title":"新春试笔",
        "date":"20050214",
        "content":"凄凉。\n悲凉。\n苍凉。\n我想，天堂也无非是这样。"
    },
    {
        "title":"雪朝",
        "date":"",
        "content":"雪落北京上海与否，我尚不知\n雪落到了平凉\n雪落庄浪静宁与否，我尚不知\n雪落到了崆峒\n雪落到了你的心上与否，我尚不知\n雪落到了我的心上"
    }
]