[
    {
        "title":"家里的水变大了",
        "date":"2012",
        "content":"家里的水确定变大了\n变得比朋友家的还大"
    },
    {
        "title":"家门口有条河",
        "date":"2012",
        "content":"我住在一楼\n门前三米就是一条河\n秦淮河\n家门口有条河\n别以为是件好事\n室友周说秦淮河\n把他的被子都熏臭了"
    },
    {
        "title":"假如你真的要给我钱",
        "date":"2010",
        "content":"我的银行账号如下：\n招商银行\n6225 8802 8027 7774\n郑功宇\n建设银行\n4367 4238 1313 0667 813\n郑功宇\n工商银行\n6222 0212 0200 9437 030\n郑功宇\n中国银行\n6013 8231 0009 0157 801\n郑功宇\n农业银行\n6228 4804 6154 1836 114\n郑功宇"
    },
    {
        "title":"假如你真的要给我钱2015",
        "date":"20151012",
        "content":"182rwEKwjGThk4VC1eXuXGyFwW1xawdfoC"
    },
    {
        "title":"结婚，我们要在炎热的阳光下结婚",
        "date":"20150309",
        "content":"我计划于六月结婚\n或者七月\n八月\n九月也行\n不该再晚了\n否则冬天就要来了\n冬天一来一切完蛋\n当然，如果你真的嫁给我\n从一月到十二月\n任何一个月都可以\n比如三月\n或者十一月\n四月\n或者九月\n但我还是希望在夏天\n在炎热的阳光下结婚\n比较有安全感"
    },
    {
        "title":"杰森伯恩的垃圾袋",
        "date":"2008",
        "content":"杰森伯恩\n背上垃圾袋\n开始逃跑\n那个垃圾袋\n真的很不错"
    },
    {
        "title":"结尾",
        "date":"2012",
        "content":"他拿着电话说，真的吗？\n那你坐地铁3号线到曹杨路站\n我去接你\n然后他起床穿衣刷牙洗脸出门\n快到地铁站时\n远远地看见她站在出口\n他一边向她走去一边招手\n她也看见了他，向他走来"
    },
    {
        "title":"介错人",
        "date":"2010",
        "content":"在路上别人问他\n为什么带着一把武士刀？\n他告诉别人\n他是一个介错人\n去远方\n为他的朋友介错\n什么意思呢？别人问\n就是我的朋友要切腹\n需要我帮忙砍头\n你知道吗\n这砍头一刀很难\n要在脖子上砍一半多一点\n几乎砍断\n但不能完全砍断\n所以是个技术活\n更重要的是被托付介错\n是一种荣誉\n别人听了有些惊讶\n真的吗？\n你真的是一个介错人？"
    },
    {
        "title":"金龙镖局没了，擒龙镖局也没了",
        "date":"20150309",
        "content":"一个男子\n去寻找杀父仇人报仇\n茫茫人海，无处觅\n终于病倒在路上\n一个女子救了他的命\n救命之恩，感天地\n然后不免落入俗套\n女子带男子去见爹\n不看则罢一看大惊失色\n女子的爹爹正是男子的仇人\n血海深仇非报不可\n女子救父拼命阻挡\n男子纠结攻心\n一口鲜血喷出倒地不醒\n女子及其父又倾情而救\n恩仇无解，一走了之\n人生绝望\n抱着师傅痛哭\n师傅说\n你没地儿去就待我这吧"
    },
    {
        "title":"今天不高兴",
        "date":"2007",
        "content":"今天的不高兴\n和昨天的不高兴\n大有区别\n如果昨天你问我\n为什么不高兴\n我会滔滔不绝跟你说上半天\n而今天\n你最好别问我"
    },
    {
        "title":"今天两次割破手指",
        "date":"20150716",
        "content":"如果是一次\n我不会写这首诗\n而且第二次比第一次\n要严重\n鲜血现在还在流"
    },
    {
        "title":"今天你准备洗那种澡",
        "date":"20150507",
        "content":"洗澡分快澡和慢澡\n今天我准备洗个快澡\n你呢？"
    },
    {
        "title":"今天晚些时候过去",
        "date":"2012",
        "content":"下午6点路过一家饺子馆\n朝里面望了一眼\n望见墙上的目录\n约有十几种\n他决定今天晚些时候\n到这家饺子馆\n吃素三鲜饺子\n二两还是三两到时再定\n走了几步他又觉得\n今天可能不会去了"
    },
    {
        "title":"仅仅",
        "date":"20151010",
        "content":"仅仅一瞬间，就过去了\n仅仅增加了\n命运的不确定性\n仅仅\n仅仅而已"
    },
    {
        "title":"近在咫尺",
        "date":"20150507",
        "content":"把你脱下来的内裤\n和我的手机放在一起\n今晚我们不需要它们"
    },
    {
        "title":"镜子",
        "date":"20150328",
        "content":"你对着镜子\n看到什么\n看到一个正在看着我的人\n这远远不够\n这个人还对我说了很多话\n关于真实和虚幻什么的\n关于我，他知道的很多\n我们同时在想\n对方知道的没有我多\n又或许知道的比我还多\n所以镜子里\n是一个无所不知的傻瓜\n一个和镜子外的人不一样的人\n是即将消失的人"
    },
    {
        "title":"酒后的人生观",
        "date":"2007",
        "content":"酒，让我感到虚弱\n一二三四五六七八九\n让我们想的太多\n可是那又有什么用"
    },
    {
        "title":"玖拾叁",
        "date":"20150416",
        "content":"向窗口而去\n缓缓地靠近窗口\n越靠近窗口\n窗外的世界就变得越大\n越来越大越来越大\n直到飞出窗口\n彻底进入另一个世界"
    },
    {
        "title":"就是你上次说的那个",
        "date":"2012",
        "content":"上周的有一天\n在优衣库买了条牛仔裤\n从这条路回家\n回到家发现自己双手空空\n完全不记得裤子丢哪儿了\n今天再次经过此路，想起这事儿\n他指着拐弯处那家鸭血粉丝汤馆\n对朋友说，你觉得那姑娘怎么样？\n我没有看到正脸。朋友说\n背影也很好啊，这屁股这腰\n嗯，皮肤也很光滑"
    },
    {
        "title":"咖啡机叫",
        "date":"2012",
        "content":"正在接咖啡\n钟点工阿姨问\n这咖啡机会叫吗？\n磨豆时会有声响，我说\n不是，平时，没开的时候\n那当然不会叫啊\n会！它会突然叫一声\n我在旁边洗碗\n吓一跳，她说\n有好几次了"
    }
]