[
    {
        "title":"蝴蝶",
        "date":"",
        "content":"醉心于斑驳的舞姿∶一只、一对、一群。\n仿佛乐池四周七彩灯光的旋转，\n无声。而紧绷着的脸，\n明或暗∶看谁的步履匆匆，\n转瞬即逝的停顿，摸拟风，\n风的形状如手指在抓取着一把虚空。\n\n——生活的虚空。我懂。\n现实的大地在谁的眼中晃动？挑剔着真理，\n落下不踏实的怀疑∶对应于蝴蝶，\n美在纷飞，两片音符在琴弦上翕动，\n以至打开我们身上的折叠了千年的翅膀？\n是否还会迎来这样的欣赏∶生锈的庄子\n\n躺在一株臃肿的臭椿树下，\n梦见自己变成了一只蝴蝶，\n蝴蝶又梦见自己变成了庄子，……\n是庄子梦见蝴蝶，还是蝴蝶梦见庄子？\n到底谁是谁？——这中间\n是一面镜子又是无数面镜子∶我试着\n踏进，迎面涌来迷宫内部无尽的廓道，\n一扇扇相似的门象眼睛一样打开，\n又在身后一一闭拢∶界限被混淆，\n没有了起点和终点，丈量\n这无限展开的过程，仿佛一段蛇腰，\n穿越时间隧道，或博尔赫斯盲目的呼喊。\n\n因为蝴蝶，文学想象的原型\n向我走来，翻开世界这部传奇，\n一页一页的连接和翻版；犹如薪火相传，\n当我走向我们——这盛开的一群\n彼此间形同陌路，又似曾相识。\n我们深陷的生活∶仅仅是一种迷失。"
    },
    {
        "title":"麻雀",
        "date":"",
        "content":"这加入流亡队伍中的小小跳跃。\n在梅雨天的巷子口，\n“叽叽——叽叽”，荏弱而单一的叫唤，\n随风抽出了豌豆芽。\n——我想找人饮酒、喝茶。\n问题并不在于有没有这样的朋友，\n\n受潮的心情需要设辞。我怎么就想起\n过去的一片天空，蓝得耀眼∶\n一只麻雀就是一群！\n集体的翔动，仿佛\n镶嵌在太阳转盘里的数不清的葵花籽，\n照耀着童年的村落、田野、以及\n\n环形山丘上一对交配的灰狐狸……\n谁把谁临风眺望？\n——当日子变得琐碎和进步，\n还来不及梳理，仿佛打着浑身补丁的羽毛\n我聆听到一种变迁和消逝∶\n落后或美的东西夭折于麻雀五脏俱全的体内。\n\n从突然沉寂下来的西山竹林，\n从乡村公社到纸币泛滥的\n城市∶一条条追逐的道路\n裸露鞭子的痕迹\n这加入流亡队伍的小小跳跃，\n见证着数量锐减的一种无奈∶而归宿\n\n依然不明。当吝啬和仇恨在旧式屋檐下\n眉来眼去，人类注定无法原谅自己——\n“只要年成熟，麻雀吃得几粒谷？”\n如此简单的道理与农药摆放在一起。\n一旦内心的灯盏熄灭，\n我起誓∶田鼠深潜的两豆目光将越燃越旺。"
    }
]